<?xml version="1.0" encoding="UTF-8"?>
<metrics generated="2025-06-16T12:57:25" pdepend="@package_version@" ahh="0.6875" andc="0.38095238095238" calls="648" ccn="406" ccn2="423" cloc="88" clsa="1" clsc="37" eloc="2694" fanout="65" leafs="31" lloc="1261" loc="3169" maxDIT="4" ncloc="3081" noc="38" nof="9" noi="0" nom="176" nop="4" roots="5">
  <files>
    <file name="/Users/www/zd/phpqa/RoboFile.php" loc="10" cloc="0" eloc="7" lloc="3" ncloc="10"/>
    <file name="/Users/www/zd/phpqa/src/CodeAnalysisTasks.php" loc="218" cloc="22" eloc="182" lloc="75" ncloc="196"/>
    <file name="/Users/www/zd/phpqa/src/Config.php" loc="148" cloc="7" eloc="125" lloc="70" ncloc="141"/>
    <file name="/Users/www/zd/phpqa/src/IgnoredPaths.php" loc="111" cloc="1" eloc="93" lloc="50" ncloc="110"/>
    <file name="/Users/www/zd/phpqa/src/Options.php" loc="123" cloc="9" eloc="100" lloc="60" ncloc="114"/>
    <file name="/Users/www/zd/phpqa/src/OutputMode.php" loc="12" cloc="0" eloc="9" lloc="5" ncloc="12"/>
    <file name="/Users/www/zd/phpqa/src/RunningTool.php" loc="155" cloc="1" eloc="132" lloc="74" ncloc="154"/>
    <file name="/Users/www/zd/phpqa/tests/Config/ConfigTest.php" loc="158" cloc="1" eloc="138" lloc="102" ncloc="157"/>
    <file name="/Users/www/zd/phpqa/tests/IgnoredPathsTest.php" loc="137" cloc="2" eloc="128" lloc="15" ncloc="135"/>
    <file name="/Users/www/zd/phpqa/tests/OptionsTest.php" loc="163" cloc="6" eloc="139" lloc="51" ncloc="157"/>
    <file name="/Users/www/zd/phpqa/tests/PathsTest.php" loc="15" cloc="0" eloc="12" lloc="6" ncloc="15"/>
    <file name="/Users/www/zd/phpqa/tests/Report/ReportTest.php" loc="51" cloc="1" eloc="41" lloc="21" ncloc="50"/>
    <file name="/Users/www/zd/phpqa/tests/RunningToolTest.php" loc="143" cloc="5" eloc="121" lloc="49" ncloc="138"/>
    <file name="/Users/www/zd/phpqa/src/paths.php" loc="57" cloc="0" eloc="48" lloc="32" ncloc="57"/>
    <file name="/Users/www/zd/phpqa/src/report.php" loc="84" cloc="0" eloc="72" lloc="51" ncloc="84"/>
    <file name="/Users/www/zd/phpqa/src/Task/AssetsLoader.php" loc="62" cloc="1" eloc="53" lloc="34" ncloc="61"/>
    <file name="/Users/www/zd/phpqa/src/Task/NonParallelExecV0.php" loc="42" cloc="1" eloc="33" lloc="18" ncloc="41"/>
    <file name="/Users/www/zd/phpqa/src/Task/NonParallelExecV1.php" loc="70" cloc="10" eloc="50" lloc="34" ncloc="60"/>
    <file name="/Users/www/zd/phpqa/src/Task/ParallelExec.php" loc="17" cloc="4" eloc="10" lloc="4" ncloc="13"/>
    <file name="/Users/www/zd/phpqa/src/Task/RoboAdapter.php" loc="40" cloc="0" eloc="35" lloc="18" ncloc="40"/>
    <file name="/Users/www/zd/phpqa/src/Task/TableSummary.php" loc="75" cloc="1" eloc="62" lloc="30" ncloc="74"/>
    <file name="/Users/www/zd/phpqa/src/Task/TableVersions.php" loc="31" cloc="0" eloc="25" lloc="12" ncloc="31"/>
    <file name="/Users/www/zd/phpqa/src/Tools/AnalyzeResults.php" loc="60" cloc="3" eloc="51" lloc="21" ncloc="57"/>
    <file name="/Users/www/zd/phpqa/src/Tools/GetVersions.php" loc="181" cloc="0" eloc="162" lloc="75" ncloc="181"/>
    <file name="/Users/www/zd/phpqa/src/Tools/Tool.php" loc="56" cloc="5" eloc="42" lloc="28" ncloc="51"/>
    <file name="/Users/www/zd/phpqa/src/Tools/Tools.php" loc="107" cloc="1" eloc="93" lloc="52" ncloc="106"/>
    <file name="/Users/www/zd/phpqa/tests/GetVersionsTest.php" loc="60" cloc="3" eloc="49" lloc="13" ncloc="57"/>
    <file name="/Users/www/zd/phpqa/src/Tools/Analyzer/Deptrac.php" loc="34" cloc="0" eloc="29" lloc="12" ncloc="34"/>
    <file name="/Users/www/zd/phpqa/src/Tools/Analyzer/ParallelLint.php" loc="24" cloc="0" eloc="19" lloc="5" ncloc="24"/>
    <file name="/Users/www/zd/phpqa/src/Tools/Analyzer/Pdepend.php" loc="32" cloc="0" eloc="28" lloc="9" ncloc="32"/>
    <file name="/Users/www/zd/phpqa/src/Tools/Analyzer/PhpCsFixer.php" loc="53" cloc="0" eloc="48" lloc="19" ncloc="53"/>
    <file name="/Users/www/zd/phpqa/src/Tools/Analyzer/PhpMetrics.php" loc="43" cloc="0" eloc="38" lloc="19" ncloc="43"/>
    <file name="/Users/www/zd/phpqa/src/Tools/Analyzer/PhpMetricsV2.php" loc="43" cloc="0" eloc="36" lloc="20" ncloc="43"/>
    <file name="/Users/www/zd/phpqa/src/Tools/Analyzer/Phpcpd.php" loc="47" cloc="0" eloc="43" lloc="18" ncloc="47"/>
    <file name="/Users/www/zd/phpqa/src/Tools/Analyzer/Phpcs.php" loc="49" cloc="1" eloc="43" lloc="17" ncloc="48"/>
    <file name="/Users/www/zd/phpqa/src/Tools/Analyzer/Phploc.php" loc="25" cloc="0" eloc="21" lloc="7" ncloc="25"/>
    <file name="/Users/www/zd/phpqa/src/Tools/Analyzer/Phpmd.php" loc="36" cloc="1" eloc="30" lloc="9" ncloc="35"/>
    <file name="/Users/www/zd/phpqa/src/Tools/Analyzer/Phpstan.php" loc="109" cloc="1" eloc="95" lloc="34" ncloc="108"/>
    <file name="/Users/www/zd/phpqa/src/Tools/Analyzer/Phpunit.php" loc="50" cloc="0" eloc="44" lloc="23" ncloc="50"/>
    <file name="/Users/www/zd/phpqa/src/Tools/Analyzer/Psalm.php" loc="91" cloc="0" eloc="76" lloc="43" ncloc="91"/>
    <file name="/Users/www/zd/phpqa/src/Tools/Analyzer/SecurityChecker.php" loc="40" cloc="0" eloc="33" lloc="14" ncloc="40"/>
    <file name="/Users/www/zd/phpqa/tests/Tools/Analyzer/PhpstanTest.php" loc="107" cloc="1" eloc="99" lloc="9" ncloc="106"/>
  </files>
  <package name="Edge\QA" noc="12" noi="0" nom="104" nof="9" cr="0.15" rcr="0.38678571428571">
    <class name="RoboFile" fqname="Edge\QA\RoboFile" start="5" end="9" loc="5" cloc="0" eloc="0" lloc="0" ncloc="5" dit="2" noam="0" nocc="0" noom="0" nom="0" cr="0.15" rcr="0.2775" ca="0" cbo="0" ce="0" impl="0" cis="0" csz="0" npm="0" vars="0" varsi="0" varsnp="0" wmc="0" wmci="0" wmcnp="0">
      <file name="/Users/www/zd/phpqa/RoboFile.php"/>
    </class>
    <trait name="CodeAnalysisTasks" fqname="Edge\QA\CodeAnalysisTasks" start="7" end="217" ca="0" cbo="9" ce="9" impl="0" cis="2" csz="9" npm="2" vars="0" varsi="0" varsnp="0" wmc="29" wmci="29" wmcnp="3">
      <file name="/Users/www/zd/phpqa/src/CodeAnalysisTasks.php"/>
      <method name="tools" start="18" end="26" ccn="1" ccn2="1" loc="9" cloc="0" eloc="5" lloc="3" ncloc="9" npath="1" hnt="20" hnd="13" hv="74.008794362822" hd="5.1428571428571" hl="0.19444444444444" he="380.61665672308" ht="21.145369817949" hb="0.017506685855532" hi="14.390598903882" mi="71.529444086767"/>
      <method name="ci" start="41" end="63" ccn="2" ccn2="2" loc="23" cloc="0" eloc="10" lloc="7" ncloc="23" npath="2" hnt="28" hnd="16" hv="112" hd="7" hl="0.14285714285714" he="784" ht="43.555555555556" hb="0.02834149707084" hi="16" mi="63.568378574715"/>
      <method name="normalizeCliOptions" start="65" end="73" ccn="4" ccn2="5" loc="9" cloc="0" eloc="8" lloc="5" ncloc="9" npath="12" hnt="44" hnd="21" hv="193.26196660227" hd="13.75" hl="0.072727272727273" he="2657.3520407812" ht="147.63066893229" hb="0.063950627034233" hi="14.055415752892" mi="63.619885766547"/>
      <method name="loadConfig" start="75" end="127" ccn="7" ccn2="7" loc="53" cloc="2" eloc="50" lloc="18" ncloc="51" npath="24" hnt="175" hnd="70" hv="1072.6245279654" hd="14.666666666667" hl="0.068181818181818" he="15731.826410159" ht="873.99035611993" hb="0.20928182268294" hi="73.133490543093" mi="40.777974146777"/>
      <method name="ciClean" start="129" end="137" ccn="3" ccn2="3" loc="9" cloc="0" eloc="8" lloc="4" ncloc="9" npath="3" hnt="18" hnd="10" hv="59.794705707973" hd="5.5" hl="0.18181818181818" he="328.87088139385" ht="18.27060452188" hb="0.015881652656544" hi="10.871764674177" mi="67.456302913107"/>
      <method name="runTools" start="139" end="147" ccn="2" ccn2="2" loc="9" cloc="0" eloc="8" lloc="5" ncloc="9" npath="2" hnt="32" hnd="19" hv="135.93368043019" hd="5.25" hl="0.19047619047619" he="713.65182225852" ht="39.647323458807" hb="0.026619690270194" hi="25.892129605751" mi="65.093437418531"/>
      <method name="toolToExec" start="150" end="162" ccn="3" ccn2="3" loc="13" cloc="0" eloc="12" lloc="7" ncloc="13" npath="3" hnt="53" hnd="25" hv="246.12437805806" hd="16.791666666667" hl="0.059553349875931" he="4132.8385148916" ht="229.6021397162" hb="0.085844215484652" hi="14.657531199487" mi="59.312374164518"/>
      <method name="buildHtmlReport" start="164" end="210" ccn="5" ccn2="5" loc="47" cloc="0" eloc="45" lloc="11" ncloc="47" npath="9" hnt="189" hnd="70" hv="1158.4344902026" hd="19.211538461538" hl="0.052052052052052" he="22255.3087637" ht="1236.4060424278" hb="0.26373503614074" hi="60.298892382918" mi="41.811098672946"/>
      <method name="buildSummary" start="212" end="216" ccn="1" ccn2="1" loc="5" cloc="0" eloc="4" lloc="2" ncloc="5" npath="1" hnt="18" hnd="13" hv="66.60791492654" hd="6.4166666666667" hl="0.15584415584416" he="427.4007874453" ht="23.744488191405" hb="0.018913371679784" hi="10.380454274266" mi="73.963830176072"/>
    </trait>
    <class name="Config" fqname="Edge\QA\Config" start="7" end="147" loc="141" cloc="7" eloc="105" lloc="54" ncloc="134" dit="0" noam="0" nocc="0" noom="0" nom="12" cr="0.15" rcr="0.15" ca="4" cbo="2" ce="2" impl="0" cis="7" csz="14" npm="7" vars="2" varsi="2" varsnp="0" wmc="28" wmci="28" wmcnp="14">
      <file name="/Users/www/zd/phpqa/src/Config.php"/>
      <method name="__construct" start="12" end="16" ccn="2" ccn2="2" loc="5" cloc="0" eloc="4" lloc="2" ncloc="5" npath="2" hnt="15" hnd="13" hv="55.506595772116" hd="5.25" hl="0.19047619047619" he="291.40962780361" ht="16.189423766867" hb="0.014651474810021" hi="10.572684908975" mi="74.383755378018"/>
      <method name="loadUserConfig" start="18" end="26" ccn="3" ccn2="3" loc="9" cloc="1" eloc="7" lloc="4" ncloc="8" npath="4" hnt="31" hnd="20" hv="133.97977094151" hd="8.5" hl="0.11764705882353" he="1138.8280530028" ht="63.268225166823" hb="0.036351096573821" hi="15.762325993119" mi="66.26799631173"/>
      <method name="loadConfig" start="28" end="41" ccn="3" ccn2="3" loc="14" cloc="0" eloc="13" lloc="7" ncloc="14" npath="3" hnt="51" hnd="26" hv="239.7224256252" hd="12.857142857143" hl="0.077777777777778" he="3082.1454723239" ht="171.230304018" hb="0.07059612019604" hi="18.645077548626" mi="58.634219648961"/>
      <method name="mergeConfigs" start="45" end="53" ccn="3" ccn2="3" loc="9" cloc="0" eloc="8" lloc="5" ncloc="9" npath="3" hnt="42" hnd="18" hv="175.13685006058" hd="19.642857142857" hl="0.050909090909091" he="3440.1881261899" ht="191.12156256611" hb="0.075962667498695" hi="8.9160578212657" mi="64.188359735509"/>
      <method name="getCustomBinary" start="55" end="62" ccn="2" ccn2="2" loc="8" cloc="0" eloc="7" lloc="4" ncloc="8" npath="2" hnt="21" hnd="15" hv="82.044702507779" hd="11.25" hl="0.088888888888889" he="923.00290321251" ht="51.277939067362" hb="0.031599542140709" hi="7.2928624451359" mi="67.893848817994"/>
      <method name="value" start="64" end="72" ccn="1" ccn2="1" loc="9" cloc="0" eloc="8" lloc="3" ncloc="9" npath="1" hnt="12" hnd="9" hv="38.039100017308" hd="9" hl="0.11111111111111" he="342.35190015577" ht="19.019550008654" hb="0.016312752250359" hi="4.2265666685897" mi="69.100731705465"/>
      <method name="path" start="74" end="86" ccn="2" ccn2="2" loc="13" cloc="0" eloc="12" lloc="6" ncloc="13" npath="1" hnt="38" hnd="17" hv="155.32358796751" hd="18.571428571429" hl="0.053846153846154" he="2884.5809193967" ht="160.25449552204" hb="0.067546144215168" hi="8.3635778136353" mi="60.846700074271"/>
      <method name="pathsOrValues" start="88" end="102" ccn="2" ccn2="2" loc="15" cloc="0" eloc="14" lloc="6" ncloc="15" npath="2" hnt="34" hnd="18" hv="141.77745004904" hd="14.375" hl="0.069565217391304" he="2038.0508444549" ht="113.22504691416" hb="0.053582390882459" hi="9.8627791338462" mi="59.66381676622"/>
      <method name="csv" start="104" end="119" ccn="2" ccn2="2" loc="16" cloc="4" eloc="11" lloc="6" ncloc="12" npath="2" hnt="30" hnd="15" hv="117.20671786826" hd="10.857142857143" hl="0.092105263157895" he="1272.5300797125" ht="70.696115539583" hb="0.039143301219132" hi="10.795355593129" mi="62.527258927281"/>
      <method name="get" start="121" end="129" ccn="3" ccn2="3" loc="9" cloc="0" eloc="8" lloc="4" ncloc="9" npath="3" hnt="29" hnd="20" hv="125.33591475173" hd="12.75" hl="0.07843137254902" he="1598.0329130846" ht="88.779606282478" hb="0.045561976790046" hi="9.8302678236654" mi="65.205766245576"/>
      <method name="findInConfig" start="131" end="141" ccn="3" ccn2="4" loc="11" cloc="0" eloc="10" lloc="6" ncloc="11" npath="4" hnt="40" hnd="22" hv="178.37726474549" hd="17.333333333333" hl="0.057692307692308" he="3091.8725889219" ht="171.77069938455" hb="0.070744574361471" hi="10.290996043009" mi="61.884115484069"/>
      <method name="throwInvalidPath" start="143" end="146" ccn="1" ccn2="1" loc="4" cloc="0" eloc="3" lloc="1" ncloc="4" npath="1" hnt="16" hnd="13" hv="59.207035490257" hd="5.8333333333333" hl="0.17142857142857" he="345.37437369317" ht="19.187465205176" hb="0.016408623577911" hi="10.149777512616" mi="77.047409918254"/>
    </class>
    <class name="IgnoredPaths" fqname="Edge\QA\IgnoredPaths" start="5" end="110" loc="106" cloc="1" eloc="69" lloc="30" ncloc="105" dit="0" noam="0" nocc="0" noom="0" nom="15" cr="0.15" rcr="0.15" ca="2" cbo="0" ce="0" impl="0" cis="11" csz="19" npm="11" vars="4" varsi="4" varsnp="0" wmc="21" wmci="21" wmcnp="13">
      <file name="/Users/www/zd/phpqa/src/IgnoredPaths.php"/>
      <method name="__construct" start="12" end="18" ccn="1" ccn2="1" loc="7" cloc="0" eloc="6" lloc="4" ncloc="7" npath="1" hnt="26" hnd="15" hv="101.57915548582" hd="4.6666666666667" hl="0.21428571428571" he="474.03605893383" ht="26.335336607435" hb="0.020265298159505" hi="21.766961889819" mi="68.839261503171"/>
      <method name="setOS" start="20" end="23" ccn="1" ccn2="1" loc="4" cloc="0" eloc="3" lloc="1" ncloc="4" npath="1" hnt="16" hnd="14" hv="60.917678752922" hd="4.5" hl="0.22222222222222" he="274.12955438815" ht="15.22941968823" hb="0.014066389924716" hi="13.537261945094" mi="76.960794806002"/>
      <method name="csvToArray" start="25" end="30" ccn="1" ccn2="1" loc="6" cloc="0" eloc="5" lloc="3" ncloc="6" npath="1" hnt="19" hnd="13" hv="70.308354644681" hd="7.5833333333333" hl="0.13186813186813" he="533.17168938883" ht="29.620649410491" hb="0.021917455456409" hi="9.2714313817161" mi="71.685423695431"/>
      <method name="phpcs" start="32" end="35" ccn="1" ccn2="1" loc="4" cloc="0" eloc="3" lloc="1" ncloc="4" npath="1" hnt="13" hnd="11" hv="44.972611042285" hd="4.8" hl="0.20833333333333" he="215.86853300297" ht="11.992696277943" hb="0.011995130357899" hi="9.3692939671427" mi="77.883626834239"/>
      <method name="pdepend" start="37" end="43" ccn="2" ccn2="2" loc="7" cloc="0" eloc="6" lloc="3" ncloc="7" npath="2" hnt="21" hnd="15" hv="82.044702507779" hd="5.6875" hl="0.17582417582418" he="466.62924551299" ht="25.923846972944" hb="0.02005364771954" hi="14.42544219917" mi="69.354223679516"/>
      <method name="phpmd" start="45" end="51" ccn="2" ccn2="2" loc="7" cloc="0" eloc="6" lloc="3" ncloc="7" npath="2" hnt="21" hnd="15" hv="82.044702507779" hd="5.6875" hl="0.17582417582418" he="466.62924551299" ht="25.923846972944" hb="0.02005364771954" hi="14.42544219917" mi="69.354223679516"/>
      <method name="pdependWindowsFilter" start="53" end="56" ccn="1" ccn2="1" loc="4" cloc="0" eloc="3" lloc="1" ncloc="4" npath="1" hnt="23" hnd="16" hv="92" hd="5.4444444444444" hl="0.18367346938776" he="500.88888888889" ht="27.827160493827" hb="0.021023564126092" hi="16.897959183673" mi="75.707122995861"/>
      <method name="phpmetrics" start="58" end="61" ccn="1" ccn2="1" loc="4" cloc="0" eloc="3" lloc="1" ncloc="4" npath="1" hnt="11" hnd="10" hv="36.541209043761" hd="5.25" hl="0.19047619047619" he="191.84134747975" ht="10.657852637764" hb="0.011087668241344" hi="6.9602302940497" mi="78.514964679948"/>
      <method name="phpmetrics2" start="63" end="66" ccn="1" ccn2="1" loc="4" cloc="0" eloc="3" lloc="1" ncloc="4" npath="1" hnt="11" hnd="10" hv="36.541209043761" hd="5.25" hl="0.19047619047619" he="191.84134747975" ht="10.657852637764" hb="0.011087668241344" hi="6.9602302940497" mi="78.514964679948"/>
      <method name="bergmann" start="68" end="71" ccn="1" ccn2="1" loc="4" cloc="0" eloc="3" lloc="1" ncloc="4" npath="1" hnt="11" hnd="9" hv="34.869175015865" hd="7" hl="0.14285714285714" he="244.08422511106" ht="13.560234728392" hb="0.013018827926731" hi="4.9813107165522" mi="78.657394313147"/>
      <method name="parallelLint" start="73" end="76" ccn="1" ccn2="1" loc="4" cloc="0" eloc="3" lloc="1" ncloc="4" npath="1" hnt="11" hnd="9" hv="34.869175015865" hd="7" hl="0.14285714285714" he="244.08422511106" ht="13.560234728392" hb="0.013018827926731" hi="4.9813107165522" mi="78.657394313147"/>
      <method name="phpstan" start="78" end="81" ccn="1" ccn2="1" loc="4" cloc="0" eloc="3" lloc="1" ncloc="4" npath="1" hnt="5" hnd="5" hv="11.609640474437" hd="8" hl="0.125" he="92.877123795494" ht="5.1598402108608" hb="0.0068362496969366" hi="1.4512050593046" mi="82.001716149821"/>
      <method name="psalm" start="83" end="89" ccn="1" ccn2="1" loc="7" cloc="0" eloc="6" lloc="1" ncloc="7" npath="1" hnt="13" hnd="11" hv="44.972611042285" hd="7.875" hl="0.12698412698413" he="354.15931195799" ht="19.675517331" hb="0.016685703503055" hi="5.7108077514013" mi="71.316969334197"/>
      <method name="ignore" start="91" end="104" ccn="3" ccn2="3" loc="14" cloc="1" eloc="13" lloc="7" ncloc="13" npath="3" hnt="68" hnd="23" hv="307.60221301188" hd="15.769230769231" hl="0.063414634146341" he="4850.6502821104" ht="269.48057122835" hb="0.09551657065545" hi="19.506481800753" mi="57.876036118392"/>
      <method name="implode" start="106" end="109" ccn="2" ccn2="3" loc="4" cloc="0" eloc="3" lloc="1" ncloc="4" npath="3" hnt="19" hnd="15" hv="74.230921316562" hd="8.25" hl="0.12121212121212" he="612.40510086164" ht="34.022505603424" hb="0.024038347636032" hi="8.9976874323105" mi="76.090725614935"/>
    </class>
    <class name="Options" fqname="Edge\QA\Options" start="5" end="122" loc="118" cloc="9" eloc="77" lloc="41" ncloc="109" dit="0" noam="0" nocc="0" noom="0" nom="9" cr="0.15" rcr="0.15" ca="6" cbo="2" ce="2" impl="0" cis="13" csz="18" npm="6" vars="9" varsi="9" varsnp="7" wmc="22" wmci="22" wmcnp="13">
      <file name="/Users/www/zd/phpqa/src/Options.php"/>
      <method name="__construct" start="28" end="33" ccn="1" ccn2="1" loc="6" cloc="0" eloc="5" lloc="3" ncloc="6" npath="1" hnt="24" hnd="15" hv="93.765374294604" hd="5.6875" hl="0.17582417582418" he="533.29056630056" ht="29.627253683365" hb="0.021920713172023" hi="16.486219656194" mi="70.809923082097"/>
      <method name="loadOutput" start="35" end="49" ccn="3" ccn2="4" loc="15" cloc="0" eloc="14" lloc="9" ncloc="15" npath="4" hnt="75" hnd="38" hv="393.59456350827" hd="10.14" hl="0.09861932938856" he="3991.0488739738" ht="221.72493744299" hb="0.083869381965599" hi="38.816031904169" mi="56.2898246932"/>
      <method name="getCommonRootPath" start="51" end="61" ccn="2" ccn2="2" loc="11" cloc="0" eloc="10" lloc="5" ncloc="11" npath="2" hnt="41" hnd="22" hv="182.83669636413" hd="8.3076923076923" hl="0.12037037037037" he="1518.9510159482" ht="84.386167552675" hb="0.04404614705437" hi="22.008120858645" mi="62.078032685549"/>
      <method name="getAnalyzedDirs" start="63" end="66" ccn="2" ccn2="2" loc="4" cloc="0" eloc="3" lloc="1" ncloc="4" npath="2" hnt="12" hnd="10" hv="39.863137138648" hd="8.1666666666667" hl="0.12244897959184" he="325.54895329896" ht="18.086052961053" hb="0.01577452464181" hi="4.8812004659569" mi="78.115865755769"/>
      <method name="loadTools" start="68" end="81" ccn="4" ccn2="4" loc="14" cloc="0" eloc="13" lloc="8" ncloc="14" npath="6" hnt="67" hnd="30" hv="328.76166990577" hd="14.529411764706" hl="0.068825910931174" he="4776.7136745133" ht="265.3729819174" hb="0.094543472971537" hi="22.627321410519" mi="57.539232976384"/>
      <method name="buildRunningTools" start="83" end="99" ccn="4" ccn2="6" loc="17" cloc="0" eloc="16" lloc="8" ncloc="17" npath="4" hnt="84" hnd="35" hv="430.85977342338" hd="20.210526315789" hl="0.049479166666667" he="8707.9027891883" ht="483.77237717713" hb="0.14108725807992" hi="21.318582539178" mi="54.480697505978"/>
      <method name="sortTools" start="101" end="111" ccn="1" ccn2="1" loc="11" cloc="0" eloc="10" lloc="5" ncloc="11" npath="1" hnt="30" hnd="16" hv="120" hd="9" hl="0.11111111111111" he="1080" ht="60" hb="0.035088212858554" hi="13.333333333333" mi="63.493078614637"/>
      <method name="toFile" start="113" end="116" ccn="1" ccn2="1" loc="4" cloc="0" eloc="3" lloc="1" ncloc="4" npath="1" hnt="9" hnd="8" hv="27" hd="5" hl="0.2" he="135" ht="7.5" hb="0.0087720532146386" hi="5.4" mi="79.435163286757"/>
      <method name="rawFile" start="118" end="121" ccn="1" ccn2="1" loc="4" cloc="0" eloc="3" lloc="1" ncloc="4" npath="1" hnt="11" hnd="8" hv="33" hd="13.5" hl="0.074074074074074" he="445.5" ht="24.75" hb="0.019443624152848" hi="2.4444444444444" mi="78.824936610498"/>
    </class>
    <class name="OutputMode" fqname="Edge\QA\OutputMode" start="5" end="11" loc="7" cloc="0" eloc="0" lloc="0" ncloc="7" dit="0" noam="0" nocc="0" noom="0" nom="0" cr="0.15" rcr="0.15" ca="4" cbo="0" ce="0" impl="0" cis="0" csz="0" npm="0" vars="0" varsi="0" varsnp="0" wmc="0" wmci="0" wmcnp="0">
      <file name="/Users/www/zd/phpqa/src/OutputMode.php"/>
    </class>
    <class name="RunningTool" fqname="Edge\QA\RunningTool" start="7" end="154" loc="148" cloc="1" eloc="99" lloc="45" ncloc="147" dit="0" noam="0" nocc="0" noom="0" nom="14" cr="0.15" rcr="0.15" ca="6" cbo="3" ce="3" impl="0" cis="15" csz="27" npm="10" vars="13" varsi="13" varsnp="5" wmc="34" wmci="34" wmcnp="26">
      <file name="/Users/www/zd/phpqa/src/RunningTool.php"/>
      <method name="__construct" start="26" end="46" ccn="4" ccn2="4" loc="21" cloc="0" eloc="20" lloc="9" ncloc="21" npath="8" hnt="108" hnd="34" hv="549.44598685504" hd="14.586956521739" hl="0.068554396423249" he="8014.7447212985" ht="445.26359562769" hb="0.13349711328551" hi="37.666937996023" mi="51.896375850271"/>
      <method name="isInstalled" start="48" end="52" ccn="1" ccn2="2" loc="5" cloc="0" eloc="4" lloc="1" ncloc="5" npath="1" hnt="11" hnd="9" hv="34.869175015865" hd="7" hl="0.14285714285714" he="244.08422511106" ht="13.560234728392" hb="0.013018827926731" hi="4.9813107165522" mi="75.797482281733"/>
      <method name="isAtLeastOneClassInstalled" start="54" end="65" ccn="4" ccn2="4" loc="12" cloc="0" eloc="11" lloc="6" ncloc="12" npath="6" hnt="25" hnd="14" hv="95.18387305144" hd="15.3" hl="0.065359477124183" he="1456.313257687" ht="80.906292093724" hb="0.042826766019736" hi="6.2211681732967" mi="62.891158971746"/>
      <method name="hasOutput" start="67" end="73" ccn="2" ccn2="3" loc="7" cloc="0" eloc="6" lloc="3" ncloc="7" npath="3" hnt="21" hnd="17" hv="85.836719666257" hd="11.916666666667" hl="0.083916083916084" he="1022.8875760229" ht="56.827087556828" hb="0.033840025457674" hi="7.203081370595" mi="69.082323278649"/>
      <method name="buildOption" start="75" end="82" ccn="2" ccn2="3" loc="8" cloc="0" eloc="7" lloc="3" ncloc="8" npath="3" hnt="29" hnd="14" hv="110.41329273967" hd="18" hl="0.055555555555556" he="1987.4392693141" ht="110.41329273967" hb="0.052691592330182" hi="6.1340718188706" mi="66.856290537841"/>
      <method name="getAllowedErrorsCount" start="84" end="87" ccn="1" ccn2="1" loc="4" cloc="0" eloc="3" lloc="1" ncloc="4" npath="1" hnt="5" hnd="5" hv="11.609640474437" hd="8" hl="0.125" he="92.877123795494" ht="5.1598402108608" hb="0.0068362496969366" hi="1.4512050593046" mi="82.001716149821"/>
      <method name="analyzeResult" start="89" end="109" ccn="6" ccn2="8" loc="21" cloc="0" eloc="18" lloc="11" ncloc="21" npath="14" hnt="89" hnd="37" hv="463.64134954098" hd="22.095238095238" hl="0.045258620689655" he="10244.266008905" ht="569.12588938363" hb="0.15722899677575" hi="20.983767974915" mi="52.872864773853"/>
      <method name="evaluteErrorsCount" start="111" end="115" ccn="1" ccn2="2" loc="5" cloc="0" eloc="4" lloc="2" ncloc="5" npath="1" hnt="17" hnd="14" hv="64.725033674979" hd="13.75" hl="0.072727272727273" he="889.96921303096" ht="49.442734057276" hb="0.03084102008036" hi="4.7072751763621" mi="73.916527199473"/>
      <method name="areErrorsIgnored" start="117" end="120" ccn="1" ccn2="1" loc="4" cloc="0" eloc="3" lloc="1" ncloc="4" npath="1" hnt="8" hnd="8" hv="24" hd="9" hl="0.11111111111111" he="216" ht="12" hb="0.012" hi="2.6666666666667" mi="79.793333921501"/>
      <method name="getXmlFiles" start="122" end="125" ccn="1" ccn2="1" loc="4" cloc="0" eloc="3" lloc="1" ncloc="4" npath="1" hnt="5" hnd="5" hv="11.609640474437" hd="8" hl="0.125" he="92.877123795494" ht="5.1598402108608" hb="0.0068362496969366" hi="1.4512050593046" mi="82.001716149821"/>
      <method name="getEscapedXmlFile" start="127" end="130" ccn="1" ccn2="1" loc="4" cloc="0" eloc="3" lloc="1" ncloc="4" npath="1" hnt="8" hnd="7" hv="22.458839376461" hd="7.5" hl="0.13333333333333" he="168.44129532346" ht="9.357849740192" hb="0.010166648149537" hi="2.9945119168614" mi="79.995159476497"/>
      <method name="getMainXml" start="132" end="135" ccn="1" ccn2="1" loc="4" cloc="0" eloc="3" lloc="1" ncloc="4" npath="1" hnt="7" hnd="7" hv="19.651484454403" hd="6.25" hl="0.16" he="122.82177784002" ht="6.8234321022233" hb="0.0082362400950509" hi="3.1442375127045" mi="80.401219851729"/>
      <method name="getHtmlRootReports" start="137" end="148" ccn="2" ccn2="2" loc="12" cloc="0" eloc="11" lloc="4" ncloc="12" npath="2" hnt="50" hnd="27" hv="237.74437510817" hd="17.230769230769" hl="0.058035714285714" he="4096.5184634024" ht="227.58435907791" hb="0.085340534062018" hi="13.797664626814" mi="60.376536351307"/>
      <method name="__toString" start="150" end="153" ccn="1" ccn2="1" loc="4" cloc="0" eloc="3" lloc="1" ncloc="4" npath="1" hnt="5" hnd="5" hv="11.609640474437" hd="8" hl="0.125" he="92.877123795494" ht="5.1598402108608" hb="0.0068362496969366" hi="1.4512050593046" mi="82.001716149821"/>
    </class>
    <class name="ConfigTest" fqname="Edge\QA\ConfigTest" start="6" end="157" loc="152" cloc="0" eloc="117" lloc="85" ncloc="152" dit="2" noam="15" nocc="0" noom="0" nom="15" cr="0.15" rcr="0.16821428571429" ca="0" cbo="1" ce="1" impl="0" cis="14" csz="16" npm="14" vars="1" varsi="1" varsnp="0" wmc="16" wmci="16" wmcnp="14">
      <file name="/Users/www/zd/phpqa/tests/Config/ConfigTest.php"/>
      <method name="testLoadDefaultConfig" start="10" end="44" ccn="1" ccn2="1" loc="35" cloc="0" eloc="34" lloc="32" ncloc="35" npath="1" hnt="339" hnd="53" hv="1941.7650340969" hd="11.489361702128" hl="0.087037037037037" he="22309.640817284" ht="1239.4244898491" hb="0.26416410057137" hi="169.00547518992" mi="43.433874691318"/>
      <method name="testBuildAbsolutePath" start="46" end="50" ccn="1" ccn2="1" loc="5" cloc="0" eloc="4" lloc="2" ncloc="5" npath="1" hnt="19" hnd="14" hv="72.339743519094" hd="4.125" hl="0.24242424242424" he="298.40144201626" ht="16.577857889792" hb="0.014884903506895" hi="17.53690751978" mi="73.712800121945"/>
      <method name="testOverrideDefaultConfig" start="52" end="60" ccn="1" ccn2="1" loc="9" cloc="0" eloc="8" lloc="6" ncloc="9" npath="1" hnt="55" hnd="24" hv="252.17293753966" hd="5.9705882352941" hl="0.16748768472906" he="1505.6207741339" ht="83.645598562993" hb="0.043788070725871" hi="42.235861459845" mi="63.348800258035"/>
      <method name="testAllowPartialUpdateOfTools" start="62" end="70" ccn="1" ccn2="1" loc="9" cloc="0" eloc="8" lloc="6" ncloc="9" npath="1" hnt="60" hnd="21" hv="263.53904536673" hd="8" hl="0.125" he="2108.3123629338" ht="117.12846460743" hb="0.054806918188103" hi="32.942380670841" mi="63.214736276968"/>
      <method name="testIgnoreNonExistentUserConfig" start="72" end="78" ccn="1" ccn2="1" loc="7" cloc="0" eloc="6" lloc="4" ncloc="7" npath="1" hnt="20" hnd="13" hv="74.008794362822" hd="5.1428571428571" hl="0.19444444444444" he="380.61665672308" ht="21.145369817949" hb="0.017506685855532" hi="14.390598903882" mi="69.80218723293"/>
      <method name="testNoExceptionWhenCwdHasNoConfig" start="80" end="85" ccn="1" ccn2="1" loc="6" cloc="0" eloc="5" lloc="3" ncloc="6" npath="1" hnt="18" hnd="13" hv="66.60791492654" hd="4.2857142857143" hl="0.23333333333333" he="285.46249254231" ht="15.859027363462" hb="0.014451450766055" hi="15.541846816193" mi="71.849838637306"/>
      <method name="testThrowExceptionWhenFileDoesNotExist" start="87" end="93" ccn="1" ccn2="1" loc="7" cloc="0" eloc="6" lloc="4" ncloc="7" npath="1" hnt="18" hnd="12" hv="64.529325012981" hd="3.9285714285714" hl="0.25454545454545" he="253.508062551" ht="14.083781252833" hb="0.013351803414779" hi="16.425646366941" mi="70.218990517498"/>
      <method name="testConfigCsvString" start="95" end="101" ccn="1" ccn2="1" loc="7" cloc="0" eloc="6" lloc="4" ncloc="7" npath="1" hnt="25" hnd="16" hv="100" hd="4.2" hl="0.23809523809524" he="420" ht="23.333333333333" hb="0.018694403210681" hi="23.809523809524" mi="68.886907386765"/>
      <method name="testUseCwdIfNoDirectoryIsSpecified" start="103" end="107" ccn="1" ccn2="1" loc="5" cloc="0" eloc="4" lloc="2" ncloc="5" npath="1" hnt="11" hnd="9" hv="34.869175015865" hd="4.375" hl="0.22857142857143" he="152.55264069441" ht="8.4751467052451" hb="0.0095168209471256" hi="7.9700971464835" mi="75.931985205709"/>
      <method name="testIgnoreInvalidBinaryDoesNotExist" start="109" end="114" ccn="1" ccn2="1" loc="6" cloc="0" eloc="5" lloc="3" ncloc="6" npath="1" hnt="22" hnd="15" hv="85.951593103387" hd="4.3333333333333" hl="0.23076923076923" he="372.45690344801" ht="20.692050191556" hb="0.017255574806497" hi="19.834983023859" mi="71.0745190823"/>
      <method name="testToolAndBinaryNameMightNotMatch" start="116" end="121" ccn="1" ccn2="1" loc="6" cloc="0" eloc="5" lloc="3" ncloc="6" npath="1" hnt="22" hnd="15" hv="85.951593103387" hd="4.3333333333333" hl="0.23076923076923" he="372.45690344801" ht="20.692050191556" hb="0.017255574806497" hi="19.834983023859" mi="71.0745190823"/>
      <method name="testMultipleConfig" start="123" end="132" ccn="1" ccn2="1" loc="10" cloc="0" eloc="8" lloc="6" ncloc="10" npath="1" hnt="57" hnd="25" hv="264.69980281716" hd="5.8333333333333" hl="0.17142857142857" he="1544.0821831001" ht="85.782343505561" hb="0.044530648496954" hi="45.37710905437" mi="63.201371889128"/>
      <method name="testAutodetectConfigInCurrentDirectory" start="134" end="139" ccn="1" ccn2="1" loc="6" cloc="0" eloc="5" lloc="3" ncloc="6" npath="1" hnt="22" hnd="16" hv="88" hd="3.6" hl="0.27777777777778" he="316.8" ht="17.6" hb="0.015490622145573" hi="24.444444444444" mi="71.002897300164"/>
      <method name="testIgnoreAutodetectedConfigIfUserConfigIsSpecified" start="141" end="147" ccn="1" ccn2="1" loc="7" cloc="0" eloc="6" lloc="4" ncloc="7" npath="1" hnt="33" hnd="18" hv="137.6075250476" hd="6.0454545454545" hl="0.16541353383459" he="831.90003778774" ht="46.216668765986" hb="0.029484437127531" hi="22.762147000354" mi="67.916132992331"/>
      <method name="shouldStopPhpqa" start="149" end="156" ccn="2" ccn2="2" loc="8" cloc="0" eloc="7" lloc="3" ncloc="8" npath="2" hnt="19" hnd="13" hv="70.308354644681" hd="7" hl="0.14285714285714" he="492.15848251277" ht="27.342137917376" hb="0.020778557530766" hi="10.044050663526" mi="68.363289056096"/>
    </class>
    <class name="IgnoredPathsTest" fqname="Edge\QA\IgnoredPathsTest" start="5" end="136" loc="132" cloc="2" eloc="118" lloc="9" ncloc="130" dit="2" noam="4" nocc="0" noom="0" nom="4" cr="0.15" rcr="0.16821428571429" ca="0" cbo="1" ce="1" impl="0" cis="3" csz="5" npm="3" vars="1" varsi="1" varsnp="0" wmc="6" wmci="6" wmcnp="5">
      <file name="/Users/www/zd/phpqa/tests/IgnoredPathsTest.php"/>
      <method name="ignore" start="9" end="14" ccn="1" ccn2="1" loc="6" cloc="0" eloc="5" lloc="3" ncloc="6" npath="1" hnt="18" hnd="14" hv="68.532388597037" hd="5.5" hl="0.18181818181818" he="376.9281372837" ht="20.940452071317" hb="0.01739339864462" hi="12.46043429037" mi="71.763223525053"/>
      <method name="testNoOptionWhenNothingIsIgnored" start="17" end="24" ccn="2" ccn2="2" loc="8" cloc="0" eloc="7" lloc="3" ncloc="8" npath="2" hnt="45" hnd="20" hv="194.48676426993" hd="14" hl="0.071428571428571" he="2722.814699779" ht="151.26748332106" hb="0.064996624528732" hi="13.891911733567" mi="65.269217666419"/>
      <method name="testIgnoreDirectoriesAndFiles" start="27" end="38" ccn="2" ccn2="2" loc="12" cloc="0" eloc="11" lloc="2" ncloc="12" npath="2" hnt="46" hnd="22" hv="205.13385445732" hd="8.6538461538462" hl="0.11555555555556" he="1775.1968174191" ht="98.622045412171" hb="0.048870084020314" hi="23.704356515068" mi="60.825175710279"/>
      <method name="provideTools" start="40" end="135" ccn="1" ccn2="1" loc="96" cloc="0" eloc="95" lloc="1" ncloc="96" npath="1" hnt="210" hnd="55" hv="1214.0855398402" hd="10.63829787234" hl="0.094" he="12915.803615321" ht="717.54464529561" hb="0.18349590099325" hi="114.12404074498" mi="35.127551414363"/>
    </class>
    <class name="OptionsTest" fqname="Edge\QA\OptionsTest" start="6" end="162" loc="157" cloc="5" eloc="107" lloc="34" ncloc="152" dit="2" noam="15" nocc="0" noom="0" nom="15" cr="0.15" rcr="0.16821428571429" ca="0" cbo="1" ce="1" impl="0" cis="13" csz="16" npm="13" vars="1" varsi="1" varsnp="0" wmc="16" wmci="16" wmcnp="13">
      <file name="/Users/www/zd/phpqa/tests/OptionsTest.php"/>
      <method name="setUp" start="22" end="25" ccn="1" ccn2="1" loc="4" cloc="0" eloc="3" lloc="1" ncloc="4" npath="1" hnt="7" hnd="7" hv="19.651484454403" hd="6.25" hl="0.16" he="122.82177784002" ht="6.8234321022233" hb="0.0082362400950509" hi="3.1442375127045" mi="80.401219851729"/>
      <method name="overrideOptions" start="27" end="30" ccn="1" ccn2="1" loc="4" cloc="0" eloc="3" lloc="1" ncloc="4" npath="1" hnt="11" hnd="10" hv="36.541209043761" hd="5.25" hl="0.19047619047619" he="191.84134747975" ht="10.657852637764" hb="0.011087668241344" hi="6.9602302940497" mi="78.514964679948"/>
      <method name="testEscapePaths" start="32" end="38" ccn="1" ccn2="1" loc="7" cloc="0" eloc="6" lloc="4" ncloc="7" npath="1" hnt="42" hnd="16" hv="168" hd="6.9" hl="0.14492753623188" he="1159.2" ht="64.4" hb="0.036783325779321" hi="24.347826086957" mi="67.309288833689"/>
      <method name="testRespectToolsOrderDefinedInOption" start="40" end="45" ccn="1" ccn2="1" loc="6" cloc="0" eloc="5" lloc="3" ncloc="6" npath="1" hnt="43" hnd="21" hv="188.86964917949" hd="8" hl="0.125" he="1510.9571934359" ht="83.942066301994" hb="0.04389147599761" hi="23.608706147436" mi="68.680473069792"/>
      <method name="testIgnorePdependInCliOutput" start="47" end="52" ccn="1" ccn2="1" loc="6" cloc="0" eloc="5" lloc="3" ncloc="6" npath="1" hnt="43" hnd="19" hv="182.66088307807" hd="9.8181818181818" hl="0.10185185185185" he="1793.3977611302" ht="99.633208951677" hb="0.049203556365982" hi="18.604349202396" mi="68.782118638843"/>
      <method name="testIsSuggestedToolInstalled" start="55" end="59" ccn="1" ccn2="1" loc="5" cloc="0" eloc="4" lloc="2" ncloc="5" npath="1" hnt="23" hnd="17" hv="94.011645348758" hd="5.7777777777778" hl="0.17307692307692" he="543.17839534838" ht="30.176577519354" hb="0.022190839746318" hi="16.271246310362" mi="72.915938193668"/>
      <method name="provideInternalClass" start="61" end="81" ccn="1" ccn2="1" loc="21" cloc="0" eloc="20" lloc="1" ncloc="21" npath="1" hnt="62" hnd="18" hv="258.53535008942" hd="17.2" hl="0.058139534883721" he="4446.8080215381" ht="247.04489008545" hb="0.090138639518348" hi="15.031125005199" mi="54.592379242221"/>
      <method name="testBuildOutput" start="84" end="90" ccn="1" ccn2="1" loc="7" cloc="0" eloc="6" lloc="4" ncloc="7" npath="1" hnt="32" hnd="17" hv="130.79881092001" hd="4.6363636363636" hl="0.2156862745098" he="606.43085062914" ht="33.69060281273" hb="0.023881756713923" hi="28.211508237649" mi="68.070446074908"/>
      <method name="provideOutputs" start="92" end="108" ccn="1" ccn2="1" loc="17" cloc="0" eloc="16" lloc="1" ncloc="17" npath="1" hnt="48" hnd="16" hv="192" hd="10.888888888889" hl="0.091836734693878" he="2090.6666666667" ht="116.14814814815" hb="0.054500682629716" hi="17.632653061224" mi="57.611161850977"/>
      <method name="testExecute" start="111" end="115" ccn="1" ccn2="1" loc="5" cloc="0" eloc="4" lloc="2" ncloc="5" npath="1" hnt="16" hnd="13" hv="59.207035490257" hd="3.8571428571429" hl="0.25925925925926" he="228.36999403385" ht="12.687221890769" hb="0.012453882740671" hi="15.349972164141" mi="74.322000810816"/>
      <method name="provideExecutionMode" start="117" end="124" ccn="1" ccn2="1" loc="8" cloc="0" eloc="7" lloc="1" ncloc="8" npath="1" hnt="32" hnd="15" hv="125.02049905947" hd="9.625" hl="0.1038961038961" he="1203.3223034474" ht="66.851239080412" hb="0.037710884852882" hi="12.989142759426" mi="66.747468690277"/>
      <method name="testBuildRootPath" start="127" end="131" ccn="1" ccn2="1" loc="5" cloc="0" eloc="4" lloc="2" ncloc="5" npath="1" hnt="20" hnd="15" hv="78.13781191217" hd="5.25" hl="0.19047619047619" he="410.22351253889" ht="22.79019514105" hb="0.018403161805823" hi="14.883392745175" mi="73.478342746787"/>
      <method name="provideAnalyzedDir" start="133" end="142" ccn="1" ccn2="1" loc="10" cloc="0" eloc="9" lloc="2" ncloc="10" npath="1" hnt="52" hnd="24" hv="238.4180500375" hd="13.961538461538" hl="0.071625344352617" he="3328.6827755236" ht="184.92682086242" hb="0.074312239764736" hi="17.076774933815" mi="62.40352543286"/>
      <method name="testLoadAllowedErrorsCount" start="144" end="150" ccn="1" ccn2="1" loc="7" cloc="0" eloc="6" lloc="4" ncloc="7" npath="1" hnt="49" hnd="22" hv="218.51214931323" hd="8.5714285714286" hl="0.11666666666667" he="1872.9612798277" ht="104.05340443487" hb="0.050648269500613" hi="25.493084086543" mi="66.509894850283"/>
      <method name="buildRunningTools" start="152" end="161" ccn="2" ccn2="2" loc="10" cloc="0" eloc="9" lloc="3" ncloc="10" npath="2" hnt="28" hnd="19" hv="118.94197037642" hd="11.6875" hl="0.085561497326203" he="1390.1342787744" ht="77.229682154134" hb="0.041519289560268" hi="10.176853080335" mi="64.383658508598"/>
    </class>
    <class name="PathsTest" fqname="Edge\QA\PathsTest" start="5" end="14" loc="10" cloc="0" eloc="6" lloc="4" ncloc="10" dit="2" noam="1" nocc="0" noom="0" nom="1" cr="0.15" rcr="0.16821428571429" ca="0" cbo="0" ce="0" impl="0" cis="1" csz="1" npm="1" vars="0" varsi="0" varsnp="0" wmc="1" wmci="1" wmcnp="1">
      <file name="/Users/www/zd/phpqa/tests/PathsTest.php"/>
      <method name="testPathToBinaryIsEscaped" start="7" end="13" ccn="1" ccn2="1" loc="7" cloc="0" eloc="6" lloc="4" ncloc="7" npath="1" hnt="37" hnd="19" hv="157.17331799741" hd="6.125" hl="0.16326530612245" he="962.68657273415" ht="53.48258737412" hb="0.032498901998964" hi="25.660949877129" mi="67.511860297202"/>
    </class>
    <class name="ReportTest" fqname="Edge\QA\ReportTest" start="5" end="50" loc="46" cloc="1" eloc="27" lloc="11" ncloc="45" dit="2" noam="6" nocc="0" noom="0" nom="6" cr="0.15" rcr="0.16821428571429" ca="0" cbo="0" ce="0" impl="0" cis="6" csz="9" npm="6" vars="3" varsi="3" varsnp="0" wmc="7" wmci="7" wmcnp="7">
      <file name="/Users/www/zd/phpqa/tests/Report/ReportTest.php"/>
      <method name="setUp" start="11" end="15" ccn="1" ccn2="1" loc="5" cloc="0" eloc="4" lloc="2" ncloc="5" npath="1" hnt="14" hnd="10" hv="46.506993328423" hd="4" hl="0.25" he="186.02797331369" ht="10.334887406316" hb="0.010862528153285" hi="11.626748332106" mi="75.056197271079"/>
      <method name="testConvertTwigToHtml" start="17" end="21" ccn="1" ccn2="1" loc="5" cloc="0" eloc="4" lloc="2" ncloc="5" npath="1" hnt="23" hnd="14" hv="87.569163207325" hd="5.25" hl="0.19047619047619" he="459.73810683846" ht="25.54100593547" hb="0.01985572491286" hi="16.679840610919" mi="73.131813437052"/>
      <method name="testConvertXmlToHtml" start="24" end="28" ccn="1" ccn2="1" loc="5" cloc="0" eloc="4" lloc="2" ncloc="5" npath="1" hnt="27" hnd="18" hv="112.58797503894" hd="8.5" hl="0.11764705882353" he="956.99778783101" ht="53.166543768389" hb="0.032370745489135" hi="13.245644122229" mi="72.367608061194"/>
      <method name="provideXml" start="30" end="36" ccn="1" ccn2="1" loc="7" cloc="0" eloc="6" lloc="1" ncloc="7" npath="1" hnt="24" hnd="14" hv="91.376518129383" hd="7.5" hl="0.13333333333333" he="685.32388597037" ht="38.073549220576" hb="0.025910511777406" hi="12.183535750584" mi="69.161143994754"/>
      <method name="testIgnoreMissingXmlDocuments" start="38" end="42" ccn="1" ccn2="1" loc="5" cloc="0" eloc="4" lloc="2" ncloc="5" npath="1" hnt="22" hnd="14" hv="83.761808285267" hd="4.875" hl="0.20512820512821" he="408.33881539068" ht="22.685489743927" hb="0.018346751908285" hi="17.18190939185" mi="73.26698838756"/>
      <method name="tearDown" start="44" end="49" ccn="2" ccn2="2" loc="6" cloc="0" eloc="5" lloc="2" ncloc="6" npath="2" hnt="11" hnd="8" hv="33" hd="5.8333333333333" hl="0.17142857142857" he="192.5" ht="10.694444444444" hb="0.011113032075279" hi="5.6571428571429" mi="73.851033040317"/>
    </class>
    <class name="RunningToolTest" fqname="Edge\QA\RunningToolTest" start="8" end="142" loc="135" cloc="4" eloc="101" lloc="33" ncloc="131" dit="2" noam="13" nocc="0" noom="0" nom="13" cr="0.15" rcr="0.16821428571429" ca="0" cbo="3" ce="3" impl="0" cis="13" csz="14" npm="13" vars="1" varsi="1" varsnp="0" wmc="14" wmci="14" wmcnp="14">
      <file name="/Users/www/zd/phpqa/tests/RunningToolTest.php"/>
      <method name="testBuildOptionWithDefinedSeparator" start="12" end="18" ccn="1" ccn2="1" loc="7" cloc="0" eloc="6" lloc="4" ncloc="7" npath="1" hnt="49" hnd="23" hv="221.65453584679" hd="6.9333333333333" hl="0.14423076923077" he="1536.8047818711" ht="85.378043437283" hb="0.044390620332542" hi="31.969404208672" mi="66.46647512782"/>
      <method name="testMarkSuccessWhenXPathIsNotDefined" start="20" end="24" ccn="1" ccn2="1" loc="5" cloc="0" eloc="4" lloc="2" ncloc="5" npath="1" hnt="25" hnd="18" hv="104.24812503606" hd="6" hl="0.16666666666667" he="625.48875021635" ht="34.749375012019" hb="0.024379516068268" hi="17.37468750601" mi="72.601641636579"/>
      <method name="testMarkFailureWhenXmlFileDoesNotExist" start="27" end="37" ccn="1" ccn2="1" loc="11" cloc="0" eloc="10" lloc="4" ncloc="11" npath="1" hnt="48" hnd="26" hv="225.62110647077" hd="7.4117647058824" hl="0.13492063492063" he="1672.2505538422" ht="92.902808546789" hb="0.046961970448888" hi="30.440942936533" mi="61.57313726172"/>
      <method name="provideAllowedErrorsForNonexistentFile" start="39" end="45" ccn="1" ccn2="1" loc="7" cloc="0" eloc="6" lloc="1" ncloc="7" npath="1" hnt="19" hnd="13" hv="70.308354644681" hd="7.5833333333333" hl="0.13186813186813" he="533.17168938883" ht="29.620649410491" hb="0.021917455456409" hi="9.2714313817161" mi="69.958166841594"/>
      <method name="testCompareAllowedCountWithErrorsCountFromXml" start="48" end="56" ccn="1" ccn2="1" loc="9" cloc="0" eloc="8" lloc="2" ncloc="9" npath="1" hnt="34" hnd="22" hv="151.62067503367" hd="5.7142857142857" hl="0.175" he="866.40385733525" ht="48.133547629736" hb="0.03029416571184" hi="26.533618130892" mi="64.895825404934"/>
      <method name="provideAllowedErrors" start="58" end="65" ccn="1" ccn2="1" loc="8" cloc="0" eloc="7" lloc="1" ncloc="8" npath="1" hnt="28" hnd="16" hv="112" hd="9" hl="0.11111111111111" he="1008" ht="56" hb="0.03351087491296" hi="12.444444444444" mi="67.081907283374"/>
      <method name="testRuntimeSelectionOfErrorXpath" start="67" end="79" ccn="1" ccn2="1" loc="13" cloc="0" eloc="12" lloc="3" ncloc="13" npath="1" hnt="47" hnd="25" hv="218.26124091941" hd="6.5882352941176" hl="0.15178571428571" he="1437.9564107632" ht="79.886467264621" hb="0.042466117737887" hi="33.128938353839" mi="59.946731136202"/>
      <method name="testMultipleXpaths" start="82" end="92" ccn="1" ccn2="1" loc="11" cloc="0" eloc="10" lloc="2" ncloc="11" npath="1" hnt="36" hnd="22" hv="160.53953827094" hd="6.2857142857143" hl="0.15909090909091" he="1009.1056691316" ht="56.061426062869" hb="0.033535375686499" hi="25.540381088559" mi="62.608018806537"/>
      <method name="provideMultipleXpaths" start="94" end="100" ccn="1" ccn2="1" loc="7" cloc="0" eloc="6" lloc="1" ncloc="7" npath="1" hnt="31" hnd="18" hv="129.26767504471" hd="8.4" hl="0.11904761904762" he="1085.8484703756" ht="60.324915020865" hb="0.035214773108597" hi="15.389008933894" mi="68.106253376134"/>
      <method name="testAnalyzeExitCodeInCliMode" start="103" end="115" ccn="2" ccn2="2" loc="13" cloc="0" eloc="12" lloc="5" ncloc="13" npath="2" hnt="47" hnd="30" hv="230.6238579936" hd="6.75" hl="0.14814814814815" he="1556.7110414568" ht="86.4839467476" hb="0.044773125845942" hi="34.166497480533" mi="59.64468675197"/>
      <method name="provideProcess" start="117" end="124" ccn="1" ccn2="1" loc="8" cloc="0" eloc="7" lloc="1" ncloc="8" npath="1" hnt="41" hnd="15" hv="160.18251441995" hd="11.375" hl="0.087912087912088" he="1822.0761015269" ht="101.22645008483" hb="0.049726713054503" hi="14.081979289666" mi="65.99381485852"/>
      <method name="testCreateUniqueIdForUserReport" start="126" end="132" ccn="1" ccn2="1" loc="7" cloc="0" eloc="6" lloc="4" ncloc="7" npath="1" hnt="33" hnd="20" hv="142.62362713128" hd="5.1153846153846" hl="0.19548872180451" he="729.57470801772" ht="40.531928223206" hb="0.027014188457585" hi="27.881310567018" mi="67.807256637402"/>
      <method name="testDynamicOutputModePhpstan" start="134" end="141" ccn="1" ccn2="1" loc="8" cloc="0" eloc="7" lloc="3" ncloc="8" npath="1" hnt="30" hnd="19" hv="127.43782540331" hd="6.1818181818182" hl="0.16176470588235" he="787.79746612954" ht="43.766525896085" hb="0.028432941949245" hi="20.614942344653" mi="66.689232079603"/>
    </class>
    <function name="buildToolBinary" start="5" end="9" ccn="3" ccn2="3" loc="5" cloc="0" eloc="4" lloc="2" ncloc="5" npath="4" hnt="30" hnd="15" hv="117.20671786826" hd="10.285714285714" hl="0.097222222222222" he="1205.5548123592" ht="66.975267353289" hb="0.037757513465995" hi="11.395097570525" mi="71.976343587627">
      <file name="/Users/www/zd/phpqa/src/paths.php"/>
    </function>
    <function name="buildSafeBinary" start="11" end="20" ccn="3" ccn2="4" loc="10" cloc="0" eloc="9" lloc="5" ncloc="10" npath="4" hnt="33" hnd="16" hv="132" hd="18.333333333333" hl="0.054545454545455" he="2420" ht="134.44444444444" hb="0.060083559844047" hi="7.2" mi="63.797889970587">
      <file name="/Users/www/zd/phpqa/src/paths.php"/>
    </function>
    <function name="escapePath" start="22" end="25" ccn="1" ccn2="1" loc="4" cloc="0" eloc="3" lloc="1" ncloc="4" npath="1" hnt="9" hnd="6" hv="23.26466250649" hd="6" hl="0.16666666666667" he="139.58797503894" ht="7.7548875021635" hb="0.0089696896482749" hi="3.8774437510817" mi="79.887962523002">
      <file name="/Users/www/zd/phpqa/src/paths.php"/>
    </function>
    <function name="commonPath" start="27" end="56" ccn="8" ccn2="8" loc="30" cloc="0" eloc="26" lloc="19" ncloc="30" npath="60" hnt="154" hnd="52" hv="877.86771659373" hd="28.790322580645" hl="0.034733893557423" he="25274.094743868" ht="1404.1163746593" hb="0.28707529386646" hi="30.491763825665" mi="47.447869772765">
      <file name="/Users/www/zd/phpqa/src/paths.php"/>
    </function>
    <function name="twigToHtml" start="9" end="20" ccn="2" ccn2="2" loc="12" cloc="0" eloc="11" lloc="7" ncloc="12" npath="2" hnt="60" hnd="27" hv="285.29325012981" hd="8.5" hl="0.11764705882353" he="2424.9926261034" ht="134.7218125613" hb="0.060166169127511" hi="33.563911779977" mi="59.822108225384">
      <file name="/Users/www/zd/phpqa/src/report.php"/>
    </function>
    <function name="xmlToHtml" start="22" end="52" ccn="5" ccn2="5" loc="31" cloc="0" eloc="26" lloc="20" ncloc="31" npath="10" hnt="99" hnd="45" hv="543.69345653664" hd="11.578125" hl="0.086369770580297" he="6294.9508014633" ht="349.71948897018" hb="0.11364237604575" hi="46.958679107078" mi="49.308322234598">
      <file name="/Users/www/zd/phpqa/src/report.php"/>
    </function>
    <function name="xmlXpaths" start="54" end="67" ccn="3" ccn2="3" loc="14" cloc="0" eloc="13" lloc="9" ncloc="14" npath="3" hnt="46" hnd="26" hv="216.22022703449" hd="12" hl="0.083333333333333" he="2594.6427244139" ht="144.14681802299" hb="0.062940538651706" hi="18.018352252874" mi="58.94799627377">
      <file name="/Users/www/zd/phpqa/src/report.php"/>
    </function>
    <function name="convertPhpErrorsToExceptions" start="69" end="76" ccn="2" ccn2="2" loc="8" cloc="0" eloc="7" lloc="4" ncloc="8" npath="2" hnt="17" hnd="11" hv="58.810337516834" hd="6" hl="0.16666666666667" he="352.862025101" ht="19.603445838945" hb="0.016644932057989" hi="9.8017229194723" mi="68.906318022213">
      <file name="/Users/www/zd/phpqa/src/report.php"/>
    </function>
    <function name="phpErrorToException" start="78" end="83" ccn="2" ccn2="2" loc="6" cloc="0" eloc="5" lloc="2" ncloc="6" npath="2" hnt="21" hnd="15" hv="82.044702507779" hd="7.4285714285714" hl="0.13461538461538" he="609.47493291493" ht="33.859718495274" hb="0.023961609014499" hi="11.044479183739" mi="71.081480533353">
      <file name="/Users/www/zd/phpqa/src/report.php"/>
    </function>
  </package>
  <package name="Edge\QA\Task" noc="6" noi="0" nom="18" nof="0" cr="0.15" rcr="0.2775">
    <class name="AssetsLoader" fqname="Edge\QA\Task\AssetsLoader" start="9" end="61" loc="53" cloc="1" eloc="40" lloc="25" ncloc="52" dit="0" noam="0" nocc="0" noom="0" nom="4" cr="0.15" rcr="0.15" ca="1" cbo="4" ce="4" impl="0" cis="2" csz="5" npm="2" vars="1" varsi="1" varsnp="0" wmc="8" wmci="8" wmcnp="4">
      <file name="/Users/www/zd/phpqa/src/Task/AssetsLoader.php"/>
      <method name="__construct" start="13" end="16" ccn="1" ccn2="1" loc="4" cloc="0" eloc="3" lloc="1" ncloc="4" npath="1" hnt="6" hnd="6" hv="15.509775004327" hd="4" hl="0.25" he="62.039100017308" ht="3.4466166676282" hb="0.0052238304343202" hi="3.8774437510817" mi="81.120955834208"/>
      <method name="__invoke" start="18" end="35" ccn="3" ccn2="3" loc="18" cloc="0" eloc="17" lloc="13" ncloc="18" npath="3" hnt="85" hnd="39" hv="449.25918860329" hd="13.16" hl="0.075987841945289" he="5912.2509220193" ht="328.45838455663" hb="0.10898849371083" hi="34.138236216056" mi="54.182704056871"/>
      <method name="downloadUrl" start="37" end="52" ccn="3" ccn2="3" loc="16" cloc="0" eloc="15" lloc="10" ncloc="16" npath="4" hnt="67" hnd="31" hv="331.93115279592" hd="14.444444444444" hl="0.069230769230769" he="4794.5610959411" ht="266.36450533006" hb="0.094778824206013" hi="22.979849039718" mi="56.288867453394"/>
      <method name="writeln" start="55" end="60" ccn="1" ccn2="1" loc="6" cloc="0" eloc="5" lloc="1" ncloc="6" npath="1" hnt="16" hnd="11" hv="55.350905898197" hd="3.75" hl="0.26666666666667" he="207.56589711824" ht="11.531438728791" hb="0.011685556848225" hi="14.760241572852" mi="72.412808236663"/>
    </class>
    <class name="NonParallelExecV0" fqname="Edge\QA\Task\NonParallelExecV0" start="10" end="41" loc="32" cloc="0" eloc="20" lloc="9" ncloc="32" dit="4" noam="3" nocc="0" noom="1" nom="4" cr="0.15" rcr="0.47799375" ca="0" cbo="3" ce="3" impl="0" cis="0" csz="5" npm="0" vars="1" varsi="1" varsnp="0" wmc="5" wmci="13" wmcnp="0">
      <file name="/Users/www/zd/phpqa/src/Task/NonParallelExecV0.php"/>
      <method name="startProgressIndicator" start="14" end="18" ccn="1" ccn2="1" loc="5" cloc="0" eloc="4" lloc="2" ncloc="5" npath="1" hnt="15" hnd="11" hv="51.891474279559" hd="3.75" hl="0.26666666666667" he="194.59302854835" ht="10.810723808242" hb="0.011193440544457" hi="13.837726474549" mi="74.723057266607"/>
      <method name="advanceProgressIndicator" start="20" end="23" ccn="1" ccn2="1" loc="4" cloc="0" eloc="3" lloc="1" ncloc="4" npath="1" hnt="6" hnd="6" hv="15.509775004327" hd="4" hl="0.25" he="62.039100017308" ht="3.4466166676282" hb="0.0052238304343202" hi="3.8774437510817" mi="81.120955834208"/>
      <method name="stopProgressIndicator" start="25" end="28" ccn="1" ccn2="1" loc="4" cloc="0" eloc="3" lloc="1" ncloc="4" npath="1" hnt="7" hnd="6" hv="18.094737505048" hd="5" hl="0.2" he="90.47368752524" ht="5.0263159736245" hb="0.0067177979841176" hi="3.6189475010096" mi="80.652193532979"/>
      <method name="printProcessResult" start="30" end="40" ccn="2" ccn2="2" loc="11" cloc="0" eloc="10" lloc="5" ncloc="11" npath="2" hnt="38" hnd="18" hv="158.45715005481" hd="7.6363636363636" hl="0.13095238095238" he="1210.0364186004" ht="67.224245477797" hb="0.037851030374984" hi="20.750341078606" mi="62.513218480074"/>
    </class>
    <class name="NonParallelExecV1" fqname="Edge\QA\Task\NonParallelExecV1" start="18" end="69" loc="52" cloc="0" eloc="41" lloc="29" ncloc="52" dit="3" noam="2" nocc="1" noom="0" nom="2" cr="0.2775" rcr="0.385875" ca="0" cbo="2" ce="2" impl="0" cis="1" csz="2" npm="1" vars="0" varsi="0" varsnp="0" wmc="9" wmci="10" wmcnp="7">
      <file name="/Users/www/zd/phpqa/src/Task/NonParallelExecV1.php"/>
      <method name="run" start="20" end="57" ccn="7" ccn2="7" loc="38" cloc="0" eloc="32" lloc="25" ncloc="38" npath="36" hnt="124" hnd="52" hv="706.8545250495" hd="20.117647058824" hl="0.049707602339181" he="14220.249856878" ht="790.01388093767" hb="0.19565167190464" hi="35.136043642811" mi="46.27414561019"/>
      <method name="printProcessResult" start="59" end="68" ccn="2" ccn2="2" loc="10" cloc="0" eloc="9" lloc="4" ncloc="10" npath="2" hnt="31" hnd="16" hv="124" hd="7.7777777777778" hl="0.12857142857143" he="964.44444444444" ht="53.58024691358" hb="0.032538452100984" hi="15.942857142857" mi="64.257016202343"/>
    </class>
    <class name="ParallelExec" fqname="Edge\QA\Task\ParallelExec" start="9" end="16" loc="8" cloc="0" eloc="4" lloc="2" ncloc="8" dit="2" noam="1" nocc="1" noom="0" nom="1" cr="0.385875" rcr="0.2775" ca="0" cbo="0" ce="0" impl="0" cis="1" csz="1" npm="1" vars="0" varsi="0" varsnp="0" wmc="1" wmci="1" wmcnp="1">
      <file name="/Users/www/zd/phpqa/src/Task/ParallelExec.php"/>
      <method name="process" start="11" end="15" ccn="1" ccn2="1" loc="5" cloc="0" eloc="4" lloc="2" ncloc="5" npath="1" hnt="12" hnd="10" hv="39.863137138648" hd="6" hl="0.16666666666667" he="239.17882283189" ht="13.287712379549" hb="0.012843810659451" hi="6.6438561897747" mi="75.524959572308"/>
    </class>
    <trait name="RoboAdapter" fqname="Edge\QA\Task\RoboAdapter" start="5" end="39" ca="0" cbo="0" ce="0" impl="0" cis="0" csz="3" npm="0" vars="0" varsi="0" varsnp="0" wmc="8" wmci="8" wmcnp="0">
      <file name="/Users/www/zd/phpqa/src/Task/RoboAdapter.php"/>
      <method name="taskPhpqaRunner" start="7" end="20" ccn="4" ccn2="4" loc="14" cloc="0" eloc="13" lloc="7" ncloc="14" npath="8" hnt="46" hnd="19" hv="195.4046656184" hd="16.666666666667" hl="0.06" he="3256.7444269734" ht="180.93024594297" hb="0.073237672012843" hi="11.724279937104" mi="59.121311580608"/>
      <method name="addArgToExec" start="22" end="29" ccn="2" ccn2="2" loc="8" cloc="0" eloc="7" lloc="3" ncloc="8" npath="2" hnt="18" hnd="11" hv="62.269769135471" hd="11.375" hl="0.087912087912088" he="708.31862391599" ht="39.351034661999" hb="0.02648690329358" hi="5.474265418503" mi="68.732502962582"/>
      <method name="isRoboVersionOne" start="31" end="38" ccn="2" ccn2="2" loc="8" cloc="0" eloc="7" lloc="4" ncloc="8" npath="2" hnt="23" hnd="15" hv="89.858483698996" hd="14" hl="0.071428571428571" he="1258.0187717859" ht="69.889931765886" hb="0.038845152103637" hi="6.4184631213569" mi="67.617209492456"/>
    </trait>
    <class name="TableSummary" fqname="Edge\QA\Task\TableSummary" start="9" end="74" loc="66" cloc="1" eloc="48" lloc="20" ncloc="65" dit="0" noam="0" nocc="0" noom="0" nom="5" cr="0.15" rcr="0.15" ca="1" cbo="3" ce="3" impl="0" cis="2" csz="6" npm="2" vars="1" varsi="1" varsnp="0" wmc="12" wmci="12" wmcnp="5">
      <file name="/Users/www/zd/phpqa/src/Task/TableSummary.php"/>
      <method name="__construct" start="13" end="16" ccn="1" ccn2="1" loc="4" cloc="0" eloc="3" lloc="1" ncloc="4" npath="1" hnt="6" hnd="6" hv="15.509775004327" hd="4" hl="0.25" he="62.039100017308" ht="3.4466166676282" hb="0.0052238304343202" hi="3.8774437510817" mi="81.120955834208"/>
      <method name="__invoke" start="18" end="44" ccn="4" ccn2="4" loc="27" cloc="0" eloc="23" lloc="11" ncloc="27" npath="6" hnt="101" hnd="46" hv="557.87975756176" hd="14.032258064516" hl="0.071264367816092" he="7828.3127270763" ht="434.90626261535" hb="0.13141880779091" hi="39.756948240033" mi="50.525992840447"/>
      <method name="result" start="46" end="60" ccn="4" ccn2="4" loc="15" cloc="0" eloc="14" lloc="6" ncloc="15" npath="8" hnt="64" hnd="29" hv="310.91078368816" hd="10.694444444444" hl="0.093506493506494" he="3325.0181033318" ht="184.72322796288" hb="0.074257687656863" hi="29.072177176036" mi="57.006924006193"/>
      <method name="getStatus" start="62" end="65" ccn="2" ccn2="2" loc="4" cloc="0" eloc="3" lloc="1" ncloc="4" npath="2" hnt="8" hnd="8" hv="24" hd="4.1666666666667" hl="0.24" he="100" ht="5.5555555555556" hb="0.0071814489667729" hi="5.76" mi="79.658830997525"/>
      <method name="writeln" start="68" end="73" ccn="1" ccn2="1" loc="6" cloc="0" eloc="5" lloc="1" ncloc="6" npath="1" hnt="16" hnd="11" hv="55.350905898197" hd="3.75" hl="0.26666666666667" he="207.56589711824" ht="11.531438728791" hb="0.011685556848225" hi="14.760241572852" mi="72.412808236663"/>
    </class>
    <class name="TableVersions" fqname="Edge\QA\Task\TableVersions" start="8" end="30" loc="23" cloc="0" eloc="15" lloc="6" ncloc="23" dit="0" noam="0" nocc="0" noom="0" nom="2" cr="0.15" rcr="0.15" ca="1" cbo="2" ce="2" impl="0" cis="2" csz="3" npm="2" vars="1" varsi="1" varsnp="0" wmc="3" wmci="3" wmcnp="3">
      <file name="/Users/www/zd/phpqa/src/Task/TableVersions.php"/>
      <method name="__construct" start="12" end="15" ccn="1" ccn2="1" loc="4" cloc="0" eloc="3" lloc="1" ncloc="4" npath="1" hnt="6" hnd="6" hv="15.509775004327" hd="4" hl="0.25" he="62.039100017308" ht="3.4466166676282" hb="0.0052238304343202" hi="3.8774437510817" mi="81.120955834208"/>
      <method name="__invoke" start="17" end="29" ccn="2" ccn2="2" loc="13" cloc="0" eloc="12" lloc="5" ncloc="13" npath="2" hnt="46" hnd="27" hv="218.72482509952" hd="9.28125" hl="0.10774410774411" he="2030.0397829549" ht="112.77998794194" hb="0.053441886198578" hi="23.566311121834" mi="59.805776152038"/>
    </class>
  </package>
  <package name="Edge\QA\Tools" noc="5" noi="0" nom="32" nof="0" cr="0.269" rcr="0.16821428571429">
    <class name="AnalyzeResults" fqname="Edge\QA\Tools\AnalyzeResults" start="7" end="59" loc="53" cloc="3" eloc="42" lloc="16" ncloc="50" dit="0" noam="0" nocc="0" noom="0" nom="2" cr="0.15" rcr="0.15" ca="1" cbo="2" ce="2" impl="0" cis="2" csz="3" npm="2" vars="1" varsi="1" varsnp="0" wmc="7" wmci="7" wmcnp="7">
      <file name="/Users/www/zd/phpqa/src/Tools/AnalyzeResults.php"/>
      <method name="__construct" start="11" end="14" ccn="1" ccn2="1" loc="4" cloc="0" eloc="3" lloc="1" ncloc="4" npath="1" hnt="6" hnd="6" hv="15.509775004327" hd="4" hl="0.25" he="62.039100017308" ht="3.4466166676282" hb="0.0052238304343202" hi="3.8774437510817" mi="81.120955834208"/>
      <method name="__invoke" start="19" end="58" ccn="6" ccn2="6" loc="40" cloc="0" eloc="39" lloc="15" ncloc="40" npath="18" hnt="158" hnd="52" hv="900.66947546629" hd="32.516129032258" hl="0.030753968253968" he="29286.284879678" ht="1627.0158266488" hb="0.31670501007585" hi="27.699160455809" mi="43.797650246133"/>
    </class>
    <class name="GetVersions" fqname="Edge\QA\Tools\GetVersions" start="7" end="180" loc="174" cloc="0" eloc="145" lloc="62" ncloc="174" dit="0" noam="0" nocc="0" noom="0" nom="11" cr="0.15" rcr="0.15" ca="3" cbo="1" ce="1" impl="0" cis="5" csz="11" npm="5" vars="0" varsi="0" varsnp="0" wmc="30" wmci="30" wmcnp="10">
      <file name="/Users/www/zd/phpqa/src/Tools/GetVersions.php"/>
      <method name="hasToolVersion" start="9" end="14" ccn="1" ccn2="1" loc="6" cloc="0" eloc="5" lloc="3" ncloc="6" npath="1" hnt="28" hnd="18" hv="116.75790004038" hd="10.625" hl="0.094117647058824" he="1240.5526879291" ht="68.919593773838" hb="0.03848476934437" hi="10.98897882733" mi="70.143024855943"/>
      <method name="__invoke" start="16" end="37" ccn="3" ccn2="3" loc="22" cloc="0" eloc="21" lloc="7" ncloc="22" npath="3" hnt="99" hnd="37" hv="515.73588319727" hd="17.95652173913" hl="0.055690072639225" he="9260.8225982813" ht="514.49014434896" hb="0.14699812272714" hi="28.721368797911" mi="51.761195118125"/>
      <method name="findComposerPackages" start="39" end="58" ccn="5" ccn2="5" loc="20" cloc="0" eloc="16" lloc="11" ncloc="20" npath="16" hnt="62" hnd="28" hv="298.05600516757" hd="19.5" hl="0.051282051282051" he="5812.0921007676" ht="322.8940055982" hb="0.10775408342476" hi="15.284923341927" mi="55.735789117151"/>
      <method name="analyzeTool" start="60" end="111" ccn="7" ccn2="7" loc="52" cloc="0" eloc="49" lloc="16" ncloc="52" npath="11" hnt="225" hnd="52" hv="1282.5989365817" hd="35.470588235294" hl="0.028192371475954" he="45494.538750517" ht="2527.4743750287" hb="0.42480040565028" hi="36.159505674776" mi="40.425709847411"/>
      <method name="normalizeVersion" start="113" end="119" ccn="2" ccn2="2" loc="7" cloc="0" eloc="6" lloc="3" ncloc="7" npath="2" hnt="21" hnd="13" hv="77.709234080963" hd="15.75" hl="0.063492063492063" he="1223.9204367752" ht="67.995579820843" hb="0.038140015893304" hi="4.9339196241881" mi="69.519316558262"/>
      <method name="groupAuthors" start="121" end="132" ccn="1" ccn2="1" loc="12" cloc="0" eloc="11" lloc="3" ncloc="12" npath="1" hnt="16" hnd="11" hv="55.350905898197" hd="6.6" hl="0.15151515151515" he="365.3159789281" ht="20.295332162672" hb="0.017034309132396" hi="8.3865008936662" mi="64.943212191106"/>
      <method name="loadVersionFromConsoleCommand" start="134" end="144" ccn="3" ccn2="3" loc="11" cloc="0" eloc="10" lloc="7" ncloc="11" npath="3" hnt="43" hnd="21" hv="188.86964917949" hd="14.090909090909" hl="0.070967741935484" he="2661.34505662" ht="147.85250314556" hb="0.064014673738001" hi="13.403652522415" mi="61.844809721797"/>
      <method name="createSymfonyProcess" start="146" end="153" ccn="2" ccn2="2" loc="8" cloc="0" eloc="7" lloc="3" ncloc="8" npath="2" hnt="21" hnd="14" hv="79.95445336321" hd="9.3333333333333" hl="0.10714285714286" he="746.24156472329" ht="41.457864706849" hb="0.027424056940772" hi="8.5665485746296" mi="67.972326584488"/>
      <method name="extractVersionFromConsole" start="155" end="169" ccn="3" ccn2="3" loc="15" cloc="0" eloc="14" lloc="7" ncloc="15" npath="3" hnt="45" hnd="25" hv="208.97352853986" hd="18.454545454545" hl="0.054187192118227" he="3856.5114812356" ht="214.25063784642" hb="0.081973818223266" hi="11.323688738613" mi="58.349585854848"/>
      <method name="normalizeSemver" start="171" end="174" ccn="1" ccn2="1" loc="4" cloc="0" eloc="3" lloc="1" ncloc="4" npath="1" hnt="12" hnd="11" hv="41.513179423648" hd="7" hl="0.14285714285714" he="290.59225596553" ht="16.144014220307" hb="0.01462406480668" hi="5.9304542033782" mi="78.127031559328"/>
      <method name="compareVersions" start="176" end="179" ccn="1" ccn2="2" loc="4" cloc="0" eloc="3" lloc="1" ncloc="4" npath="1" hnt="20" hnd="15" hv="78.13781191217" hd="6.8571428571429" hl="0.14583333333333" he="535.80213882631" ht="29.766785490351" hb="0.021989484107274" hi="11.395097570525" mi="76.069248930248"/>
    </class>
    <class name="Tool" fqname="Edge\QA\Tools\Tool" start="9" end="55" loc="47" cloc="5" eloc="24" lloc="13" ncloc="42" dit="0" noam="0" nocc="14" noom="0" nom="5" cr="1.935" rcr="0.15" ca="0" cbo="5" ce="5" impl="0" cis="3" csz="10" npm="2" vars="5" varsi="5" varsnp="1" wmc="6" wmci="6" wmcnp="2">
      <file name="/Users/www/zd/phpqa/src/Tools/Tool.php"/>
      <method name="__construct" start="22" end="28" ccn="1" ccn2="1" loc="7" cloc="0" eloc="6" lloc="4" ncloc="7" npath="1" hnt="18" hnd="12" hv="64.529325012981" hd="2.5" hl="0.4" he="161.32331253245" ht="8.9624062518029" hb="0.0098781776576745" hi="25.811730005192" mi="70.218990517498"/>
      <method name="__invoke" start="30" end="30" ccn="1" ccn2="1" loc="1" cloc="0" eloc="0" lloc="0" ncloc="1" npath="1" hnt="3" hnd="3" hv="4.7548875021635" hd="4.5" hl="0.22222222222222" he="21.396993759736" ht="1.1887218755409" hb="0.0025690974927435" hi="1.0566416671474" mi="100"/>
      <method name="saveDynamicConfig" start="32" end="38" ccn="2" ccn2="2" loc="7" cloc="0" eloc="6" lloc="4" ncloc="7" npath="2" hnt="45" hnd="27" hv="213.96993759736" hd="8.9375" hl="0.11188811188811" he="1912.3563172764" ht="106.24201762646" hb="0.051356011625682" hi="23.940692318585" mi="66.439270093564"/>
      <method name="toolVersionIs" start="40" end="49" ccn="1" ccn2="1" loc="10" cloc="0" eloc="9" lloc="4" ncloc="10" npath="1" hnt="48" hnd="29" hv="233.18308776612" hd="14" hl="0.071428571428571" he="3264.5632287257" ht="181.3646238181" hb="0.073354844640554" hi="16.655934840437" mi="62.471039423543"/>
      <method name="writeln" start="51" end="54" ccn="1" ccn2="1" loc="4" cloc="0" eloc="3" lloc="1" ncloc="4" npath="1" hnt="6" hnd="6" hv="15.509775004327" hd="4" hl="0.25" he="62.039100017308" ht="3.4466166676282" hb="0.0052238304343202" hi="3.8774437510817" mi="81.120955834208"/>
    </class>
    <class name="Tools" fqname="Edge\QA\Tools\Tools" start="9" end="106" loc="98" cloc="1" eloc="73" lloc="36" ncloc="97" dit="0" noam="0" nocc="0" noom="0" nom="8" cr="0.15" rcr="0.15" ca="1" cbo="6" ce="6" impl="0" cis="7" csz="12" npm="7" vars="4" varsi="4" varsnp="0" wmc="14" wmci="14" wmcnp="8">
      <file name="/Users/www/zd/phpqa/src/Tools/Tools.php"/>
      <method name="__construct" start="16" end="21" ccn="1" ccn2="1" loc="6" cloc="0" eloc="5" lloc="3" ncloc="6" npath="1" hnt="13" hnd="10" hv="43.185065233536" hd="4" hl="0.25" he="172.74026093414" ht="9.5966811630079" hb="0.010338902968954" hi="10.796266308384" mi="73.167563308452"/>
      <method name="loadTools" start="24" end="60" ccn="6" ccn2="6" loc="37" cloc="0" eloc="36" lloc="17" ncloc="37" npath="11" hnt="139" hnd="56" hv="807.22233416601" hd="24.9" hl="0.040160642570281" he="20099.836120734" ht="1116.657562263" hb="0.24641875344974" hi="32.418567637189" mi="44.889051276498"/>
      <method name="getExecutableTools" start="62" end="73" ccn="2" ccn2="2" loc="12" cloc="0" eloc="11" lloc="5" ncloc="12" npath="2" hnt="22" hnd="14" hv="83.761808285267" hd="13.5" hl="0.074074074074074" he="1130.7844118511" ht="62.82135621395" hb="0.036179727148566" hi="6.2045783915013" mi="63.548897879261"/>
      <method name="buildCommand" start="75" end="83" ccn="1" ccn2="1" loc="9" cloc="0" eloc="7" lloc="5" ncloc="9" npath="1" hnt="44" hnd="20" hv="190.16483617504" hd="10.227272727273" hl="0.097777777777778" he="1944.8676426993" ht="108.04820237218" hb="0.051936432237792" hi="18.593895092671" mi="65.472059099419"/>
      <method name="getReport" start="85" end="88" ccn="1" ccn2="1" loc="4" cloc="0" eloc="3" lloc="1" ncloc="4" npath="1" hnt="11" hnd="9" hv="34.869175015865" hd="8" hl="0.125" he="278.95340012692" ht="15.497411118162" hb="0.014230926802395" hi="4.3586468769832" mi="78.657394313147"/>
      <method name="getAssets" start="90" end="93" ccn="1" ccn2="1" loc="4" cloc="0" eloc="3" lloc="1" ncloc="4" npath="1" hnt="7" hnd="7" hv="19.651484454403" hd="6.25" hl="0.16" he="122.82177784002" ht="6.8234321022233" hb="0.0082362400950509" hi="3.1442375127045" mi="80.401219851729"/>
      <method name="getSummary" start="95" end="99" ccn="1" ccn2="1" loc="5" cloc="0" eloc="4" lloc="2" ncloc="5" npath="1" hnt="13" hnd="11" hv="44.972611042285" hd="4.8" hl="0.20833333333333" he="215.86853300297" ht="11.992696277943" hb="0.011995130357899" hi="9.3692939671427" mi="75.158217726801"/>
      <method name="getVersions" start="101" end="105" ccn="1" ccn2="1" loc="5" cloc="0" eloc="4" lloc="2" ncloc="5" npath="1" hnt="12" hnd="9" hv="38.039100017308" hd="8" hl="0.125" he="304.31280013846" ht="16.906266674359" hb="0.015080840917967" hi="4.7548875021635" mi="75.667389205507"/>
    </class>
    <class name="GetVersionsTest" fqname="Edge\QA\Tools\GetVersionsTest" start="5" end="59" loc="55" cloc="3" eloc="38" lloc="6" ncloc="52" dit="2" noam="6" nocc="0" noom="0" nom="6" cr="0.15" rcr="0.16821428571429" ca="0" cbo="1" ce="1" impl="0" cis="6" csz="6" npm="6" vars="0" varsi="0" varsnp="0" wmc="6" wmci="6" wmcnp="6">
      <file name="/Users/www/zd/phpqa/tests/GetVersionsTest.php"/>
      <method name="testNormalizeVersion" start="8" end="11" ccn="1" ccn2="1" loc="4" cloc="0" eloc="3" lloc="1" ncloc="4" npath="1" hnt="12" hnd="10" hv="39.863137138648" hd="3.5" hl="0.28571428571429" he="139.52097998527" ht="7.7511655547372" hb="0.0089668194253045" hi="11.3894677539" mi="78.250368679746"/>
      <method name="provideComposerVersion" start="13" end="20" ccn="1" ccn2="1" loc="8" cloc="0" eloc="7" lloc="1" ncloc="8" npath="1" hnt="26" hnd="15" hv="101.57915548582" hd="7.4375" hl="0.13445378151261" he="755.4949689258" ht="41.9719427181" hb="0.027650296731652" hi="13.657701577926" mi="67.378886641649"/>
      <method name="testCliVersion" start="23" end="26" ccn="1" ccn2="1" loc="4" cloc="0" eloc="3" lloc="1" ncloc="4" npath="1" hnt="12" hnd="10" hv="39.863137138648" hd="3.5" hl="0.28571428571429" he="139.52097998527" ht="7.7511655547372" hb="0.0089668194253045" hi="11.3894677539" mi="78.250368679746"/>
      <method name="provideCliVersion" start="28" end="41" ccn="1" ccn2="1" loc="14" cloc="0" eloc="13" lloc="1" ncloc="14" npath="1" hnt="68" hnd="30" hv="333.66856050138" hd="6.2391304347826" hl="0.1602787456446" he="2081.8016709543" ht="115.65564838635" hb="0.054346508391948" hi="53.4799783382" mi="57.897690025459"/>
      <method name="testCompareVersions" start="44" end="47" ccn="1" ccn2="1" loc="4" cloc="0" eloc="3" lloc="1" ncloc="4" npath="1" hnt="16" hnd="12" hv="57.359400011538" hd="3.2142857142857" hl="0.31111111111111" he="184.36950003709" ht="10.24275000206" hb="0.010797870897332" hi="17.845146670256" mi="77.143818652284"/>
      <method name="provideComparedVersions" start="49" end="58" ccn="1" ccn2="1" loc="10" cloc="0" eloc="9" lloc="1" ncloc="10" npath="1" hnt="60" hnd="24" hv="275.09775004327" hd="7.2058823529412" hl="0.13877551020408" he="1982.3220223706" ht="110.12900124281" hb="0.052601106804055" hi="38.17683061825" mi="61.968364972666"/>
    </class>
  </package>
  <package name="Edge\QA\Tools\Analyzer" noc="15" noi="0" nom="22" nof="0" cr="0.15" rcr="0.42048214285714">
    <class name="Deptrac" fqname="Edge\QA\Tools\Analyzer\Deptrac" start="7" end="33" loc="27" cloc="0" eloc="17" lloc="8" ncloc="27" dit="1" noam="0" nocc="0" noom="0" nom="1" cr="0.15" rcr="0.15910714285714" ca="0" cbo="0" ce="0" impl="0" cis="2" csz="2" npm="1" vars="1" varsi="4" varsnp="1" wmc="3" wmci="8" wmcnp="3">
      <file name="/Users/www/zd/phpqa/src/Tools/Analyzer/Deptrac.php"/>
      <method name="__invoke" start="15" end="32" ccn="3" ccn2="3" loc="18" cloc="0" eloc="17" lloc="8" ncloc="18" npath="4" hnt="54" hnd="26" hv="253.82374477962" hd="14.142857142857" hl="0.070707070707071" he="3589.7929618832" ht="199.43294232684" hb="0.078149285750364" hi="17.947133469266" mi="55.918956295276"/>
    </class>
    <class name="ParallelLint" fqname="Edge\QA\Tools\Analyzer\ParallelLint" start="7" end="23" loc="17" cloc="0" eloc="7" lloc="1" ncloc="17" dit="1" noam="0" nocc="0" noom="0" nom="1" cr="0.15" rcr="0.15910714285714" ca="0" cbo="0" ce="0" impl="0" cis="2" csz="2" npm="1" vars="1" varsi="4" varsnp="1" wmc="1" wmci="6" wmcnp="1">
      <file name="/Users/www/zd/phpqa/src/Tools/Analyzer/ParallelLint.php"/>
      <method name="__invoke" start="15" end="22" ccn="1" ccn2="1" loc="8" cloc="0" eloc="7" lloc="1" ncloc="8" npath="1" hnt="20" hnd="13" hv="74.008794362822" hd="8.1666666666667" hl="0.12244897959184" he="604.40515396305" ht="33.578064109058" hb="0.023828544636697" hi="9.0623013505496" mi="68.341812371408"/>
    </class>
    <class name="Pdepend" fqname="Edge\QA\Tools\Analyzer\Pdepend" start="5" end="31" loc="27" cloc="0" eloc="17" lloc="6" ncloc="27" dit="1" noam="0" nocc="0" noom="0" nom="1" cr="0.15" rcr="0.15910714285714" ca="0" cbo="0" ce="0" impl="0" cis="2" csz="2" npm="1" vars="1" varsi="4" varsnp="1" wmc="2" wmci="7" wmcnp="2">
      <file name="/Users/www/zd/phpqa/src/Tools/Analyzer/Pdepend.php"/>
      <method name="__invoke" start="13" end="30" ccn="2" ccn2="2" loc="18" cloc="0" eloc="17" lloc="6" ncloc="18" npath="2" hnt="69" hnd="32" hv="345" hd="8.6363636363636" hl="0.11578947368421" he="2979.5454545455" ht="165.5303030303" hb="0.069020603988683" hi="39.947368421053" mi="55.120182957735"/>
    </class>
    <class name="PhpCsFixer" fqname="Edge\QA\Tools\Analyzer\PhpCsFixer" start="7" end="52" loc="46" cloc="0" eloc="34" lloc="15" ncloc="46" dit="1" noam="0" nocc="0" noom="0" nom="1" cr="0.15" rcr="0.15910714285714" ca="0" cbo="0" ce="0" impl="0" cis="2" csz="2" npm="1" vars="1" varsi="4" varsnp="1" wmc="7" wmci="12" wmcnp="7">
      <file name="/Users/www/zd/phpqa/src/Tools/Analyzer/PhpCsFixer.php"/>
      <method name="__invoke" start="17" end="51" ccn="7" ccn2="7" loc="35" cloc="0" eloc="34" lloc="15" ncloc="35" npath="36" hnt="121" hnd="52" hv="689.75320589507" hd="15.111111111111" hl="0.066176470588235" he="10422.937333526" ht="579.05207408475" hb="0.15905188836948" hi="45.645432743056" mi="45.774282704118"/>
    </class>
    <class name="PhpMetrics" fqname="Edge\QA\Tools\Analyzer\PhpMetrics" start="7" end="42" loc="36" cloc="0" eloc="25" lloc="15" ncloc="36" dit="1" noam="0" nocc="0" noom="0" nom="1" cr="0.15" rcr="0.15910714285714" ca="0" cbo="0" ce="0" impl="0" cis="2" csz="2" npm="1" vars="1" varsi="4" varsnp="1" wmc="4" wmci="9" wmcnp="4">
      <file name="/Users/www/zd/phpqa/src/Tools/Analyzer/PhpMetrics.php"/>
      <method name="__invoke" start="16" end="41" ccn="4" ccn2="4" loc="26" cloc="0" eloc="25" lloc="15" ncloc="26" npath="6" hnt="114" hnd="46" hv="629.6860629905" hd="12.606060606061" hl="0.079326923076923" he="7937.8606728499" ht="440.99225960277" hb="0.13264199944681" hi="49.951057881458" mi="49.367871607179"/>
    </class>
    <class name="PhpMetricsV2" fqname="Edge\QA\Tools\Analyzer\PhpMetricsV2" start="5" end="42" loc="38" cloc="0" eloc="26" lloc="17" ncloc="38" dit="1" noam="0" nocc="0" noom="0" nom="1" cr="0.15" rcr="0.15910714285714" ca="0" cbo="0" ce="0" impl="0" cis="2" csz="2" npm="1" vars="1" varsi="4" varsnp="1" wmc="6" wmci="11" wmcnp="6">
      <file name="/Users/www/zd/phpqa/src/Tools/Analyzer/PhpMetricsV2.php"/>
      <method name="__invoke" start="12" end="41" ccn="6" ccn2="6" loc="30" cloc="0" eloc="26" lloc="17" ncloc="30" npath="24" hnt="114" hnd="45" hv="626.07125298158" hd="14.451612903226" hl="0.069196428571429" he="9047.7393979274" ht="502.65218877374" hb="0.14473452295365" hi="43.321894737565" mi="48.744808368545"/>
    </class>
    <class name="Phpcpd" fqname="Edge\QA\Tools\Analyzer\Phpcpd" start="5" end="46" loc="42" cloc="0" eloc="31" lloc="15" ncloc="42" dit="1" noam="0" nocc="0" noom="0" nom="1" cr="0.15" rcr="0.15910714285714" ca="0" cbo="0" ce="0" impl="0" cis="2" csz="2" npm="1" vars="1" varsi="4" varsnp="1" wmc="7" wmci="12" wmcnp="7">
      <file name="/Users/www/zd/phpqa/src/Tools/Analyzer/Phpcpd.php"/>
      <method name="__invoke" start="14" end="45" ccn="7" ccn2="7" loc="32" cloc="0" eloc="31" lloc="15" ncloc="32" npath="32" hnt="131" hnd="52" hv="746.75760307648" hd="18.942857142857" hl="0.052790346907994" he="14145.72259542" ht="785.87347752335" hb="0.19496747625089" hi="39.42159292259" mi="46.407927465861"/>
    </class>
    <class name="Phpcs" fqname="Edge\QA\Tools\Analyzer\Phpcs" start="5" end="48" loc="44" cloc="1" eloc="28" lloc="14" ncloc="43" dit="1" noam="0" nocc="0" noom="0" nom="1" cr="0.15" rcr="0.15910714285714" ca="0" cbo="0" ce="0" impl="0" cis="2" csz="2" npm="1" vars="1" varsi="4" varsnp="1" wmc="6" wmci="11" wmcnp="6">
      <file name="/Users/www/zd/phpqa/src/Tools/Analyzer/Phpcs.php"/>
      <method name="__invoke" start="18" end="47" ccn="6" ccn2="6" loc="30" cloc="0" eloc="28" lloc="14" ncloc="30" npath="7" hnt="128" hnd="54" hv="736.62560027692" hd="18.25" hl="0.054794520547945" he="13443.417205054" ht="746.85651139188" hb="0.18845971491273" hi="40.363046590516" mi="47.548229352779"/>
    </class>
    <class name="Phploc" fqname="Edge\QA\Tools\Analyzer\Phploc" start="5" end="24" loc="20" cloc="0" eloc="10" lloc="4" ncloc="20" dit="1" noam="0" nocc="0" noom="0" nom="1" cr="0.15" rcr="0.15910714285714" ca="0" cbo="0" ce="0" impl="0" cis="2" csz="2" npm="1" vars="1" varsi="4" varsnp="1" wmc="2" wmci="7" wmcnp="2">
      <file name="/Users/www/zd/phpqa/src/Tools/Analyzer/Phploc.php"/>
      <method name="__invoke" start="13" end="23" ccn="2" ccn2="2" loc="11" cloc="0" eloc="10" lloc="4" ncloc="11" npath="2" hnt="27" hnd="17" hv="110.36149671376" hd="9.5625" hl="0.10457516339869" he="1055.3318123253" ht="58.629545129185" hb="0.034551860042194" hi="11.541071551766" mi="63.613194546445"/>
    </class>
    <class name="Phpmd" fqname="Edge\QA\Tools\Analyzer\Phpmd" start="5" end="35" loc="31" cloc="1" eloc="15" lloc="6" ncloc="30" dit="1" noam="0" nocc="0" noom="0" nom="1" cr="0.15" rcr="0.15910714285714" ca="0" cbo="0" ce="0" impl="0" cis="2" csz="2" npm="1" vars="1" varsi="4" varsnp="1" wmc="3" wmci="8" wmcnp="3">
      <file name="/Users/www/zd/phpqa/src/Tools/Analyzer/Phpmd.php"/>
      <method name="__invoke" start="18" end="34" ccn="3" ccn2="3" loc="17" cloc="0" eloc="15" lloc="6" ncloc="17" npath="4" hnt="63" hnd="36" hv="325.70527509087" hd="9.8913043478261" hl="0.1010989010989" he="3221.6500036162" ht="178.98055575645" hb="0.072710586906948" hi="32.928445393802" mi="56.346446560761"/>
    </class>
    <class name="Phpstan" fqname="Edge\QA\Tools\Analyzer\Phpstan" start="7" end="108" loc="102" cloc="1" eloc="76" lloc="28" ncloc="101" dit="1" noam="2" nocc="0" noom="0" nom="3" cr="0.15" rcr="0.15910714285714" ca="3" cbo="2" ce="2" impl="0" cis="3" csz="4" npm="2" vars="1" varsi="4" varsnp="1" wmc="13" wmci="18" wmcnp="11">
      <file name="/Users/www/zd/phpqa/src/Tools/Analyzer/Phpstan.php"/>
      <method name="__invoke" start="20" end="61" ccn="6" ccn2="6" loc="42" cloc="0" eloc="36" lloc="16" ncloc="42" npath="32" hnt="157" hnd="64" hv="942" hd="13.775510204082" hl="0.072592592592593" he="12976.530612245" ht="720.91836734694" hb="0.18407062022726" hi="68.382222222222" mi="44.419512145739"/>
      <method name="getErrorFormatOption" start="63" end="66" ccn="2" ccn2="2" loc="4" cloc="0" eloc="3" lloc="1" ncloc="4" npath="2" hnt="12" hnd="12" hv="43.019550008654" hd="4.9" hl="0.20408163265306" he="210.7957950424" ht="11.710877502356" hb="0.011806469263365" hi="8.7795000017661" mi="77.884138404769"/>
      <method name="buildConfig" start="68" end="107" ccn="5" ccn2="5" loc="40" cloc="0" eloc="37" lloc="11" ncloc="40" npath="8" hnt="140" hnd="26" hv="658.06156053975" hd="70.4" hl="0.014204545454545" he="46327.533861999" ht="2573.7518812221" hb="0.42997004470095" hi="9.347465348576" mi="45.385250116001"/>
    </class>
    <class name="Phpunit" fqname="Edge\QA\Tools\Analyzer\Phpunit" start="7" end="49" loc="43" cloc="0" eloc="31" lloc="18" ncloc="43" dit="1" noam="1" nocc="0" noom="0" nom="2" cr="0.15" rcr="0.15910714285714" ca="0" cbo="0" ce="0" impl="0" cis="2" csz="3" npm="1" vars="1" varsi="4" varsnp="1" wmc="10" wmci="15" wmcnp="6">
      <file name="/Users/www/zd/phpqa/src/Tools/Analyzer/Phpunit.php"/>
      <method name="__invoke" start="15" end="32" ccn="6" ccn2="6" loc="18" cloc="0" eloc="17" lloc="11" ncloc="18" npath="10" hnt="90" hnd="38" hv="472.31347620992" hd="24.75" hl="0.04040404040404" he="11689.758536196" ht="649.43102978864" hb="0.17169162282505" hi="19.083372776158" mi="53.627017950936"/>
      <method name="getFile" start="34" end="48" ccn="4" ccn2="4" loc="15" cloc="0" eloc="14" lloc="7" ncloc="15" npath="4" hnt="113" hnd="35" hv="579.60898091478" hd="45.71875" hl="0.021872863978127" he="26498.998096198" ht="1472.1665608999" hb="0.2962773020568" hi="12.67770840005" mi="55.112884206094"/>
    </class>
    <class name="Psalm" fqname="Edge\QA\Tools\Analyzer\Psalm" start="8" end="90" loc="83" cloc="0" eloc="60" lloc="36" ncloc="83" dit="1" noam="2" nocc="0" noom="0" nom="3" cr="0.15" rcr="0.15910714285714" ca="0" cbo="2" ce="2" impl="0" cis="2" csz="4" npm="1" vars="1" varsi="4" varsnp="1" wmc="18" wmci="23" wmcnp="9">
      <file name="/Users/www/zd/phpqa/src/Tools/Analyzer/Psalm.php"/>
      <method name="__invoke" start="17" end="47" ccn="8" ccn2="9" loc="31" cloc="0" eloc="27" lloc="17" ncloc="31" npath="144" hnt="122" hnd="50" hv="688.55045515252" hd="14.571428571429" hl="0.068627450980392" he="10033.16377508" ht="557.39798750442" hb="0.15506151145409" hi="47.253462608506" mi="47.694492432791"/>
      <method name="updateProjectFiles" start="49" end="80" ccn="7" ccn2="8" loc="32" cloc="0" eloc="26" lloc="14" ncloc="32" npath="72" hnt="101" hnd="45" hv="554.6771627293" hd="15.25" hl="0.065573770491803" he="8458.8267316218" ht="469.93481842343" hb="0.13838387835395" hi="36.372272965856" mi="48.843992721806"/>
      <method name="simpleXMLToPrettyString" start="82" end="89" ccn="1" ccn2="1" loc="8" cloc="0" eloc="7" lloc="5" ncloc="8" npath="1" hnt="25" hnd="16" hv="100" hd="6.2222222222222" hl="0.16071428571429" he="622.22222222222" ht="34.567901234568" hb="0.024294562930371" hi="16.071428571429" mi="67.426532525243"/>
    </class>
    <class name="SecurityChecker" fqname="Edge\QA\Tools\Analyzer\SecurityChecker" start="7" end="39" loc="33" cloc="0" eloc="20" lloc="9" ncloc="33" dit="1" noam="1" nocc="0" noom="0" nom="2" cr="0.15" rcr="0.15910714285714" ca="0" cbo="0" ce="0" impl="0" cis="2" csz="3" npm="1" vars="1" varsi="4" varsnp="1" wmc="6" wmci="11" wmcnp="3">
      <file name="/Users/www/zd/phpqa/src/Tools/Analyzer/SecurityChecker.php"/>
      <method name="__invoke" start="15" end="26" ccn="2" ccn2="3" loc="12" cloc="0" eloc="10" lloc="3" ncloc="12" npath="2" hnt="25" hnd="16" hv="100" hd="9.6428571428571" hl="0.1037037037037" he="964.28571428571" ht="53.571428571429" hb="0.032534881841525" hi="10.37037037037" mi="63.913003816584"/>
      <method name="detectComposerLock" start="28" end="38" ccn="3" ccn2="3" loc="11" cloc="0" eloc="10" lloc="6" ncloc="11" npath="3" hnt="42" hnd="24" hv="192.56842503029" hd="13" hl="0.076923076923077" he="2503.3895253938" ht="139.07719585521" hb="0.061456010747657" hi="14.812955771561" mi="61.785832431628"/>
    </class>
    <class name="PhpstanTest" fqname="Edge\QA\Tools\Analyzer\PhpstanTest" start="7" end="106" loc="100" cloc="1" eloc="89" lloc="3" ncloc="99" dit="2" noam="2" nocc="0" noom="0" nom="2" cr="0.15" rcr="0.2775" ca="0" cbo="1" ce="1" impl="0" cis="2" csz="4" npm="2" vars="2" varsi="2" varsnp="0" wmc="2" wmci="2" wmcnp="2">
      <file name="/Users/www/zd/phpqa/tests/Tools/Analyzer/PhpstanTest.php"/>
      <method name="testBuildConfig" start="14" end="18" ccn="1" ccn2="1" loc="5" cloc="0" eloc="4" lloc="2" ncloc="5" npath="1" hnt="18" hnd="13" hv="66.60791492654" hd="4.2857142857143" hl="0.23333333333333" he="285.46249254231" ht="15.859027363462" hb="0.014451450766055" hi="15.541846816193" mi="73.963830176072"/>
      <method name="provideConfig" start="20" end="105" ccn="1" ccn2="1" loc="86" cloc="0" eloc="85" lloc="1" ncloc="86" npath="1" hnt="183" hnd="26" hv="860.18046841982" hd="23.394736842105" hl="0.042744656917885" he="20123.695695401" ht="1117.9830941889" hb="0.24661372300148" hi="36.768119010071" mi="37.229187211022"/>
    </class>
  </package>
</metrics>
